{"data":[{"associationFileName":"01_pass四维正畸临床病例分析沙龙第一期.mp4","associationFilePath":"/22000/【目录】PASS四维正畸临床病例分享/01_pass四维正畸临床病例分析沙龙第一期.mp4","associationFileId":513896664085116,"associationType":1,"category":1,"isDir":0,"pathId":19993,"size":0},{"associationFileName":"02_pass四维正畸临床病例分析沙龙第二期.mp4","associationFilePath":"/22000/【目录】PASS四维正畸临床病例分享/02_pass四维正畸临床病例分析沙龙第二期.mp4","associationFileId":910324338671547,"associationType":1,"category":1,"isDir":0,"pathId":19993,"size":0},{"associationFileName":"03_pass四维正畸临床病例分析沙龙第三期.mp4","associationFilePath":"/22000/【目录】PASS四维正畸临床病例分享/03_pass四维正畸临床病例分析沙龙第三期.mp4","associationFileId":241603050504178,"associationType":1,"category":1,"isDir":0,"pathId":19993,"size":0},{"associationFileName":"04_pass四维正畸临床病例分析沙龙第四期.mp4","associationFilePath":"/22000/【目录】PASS四维正畸临床病例分享/04_pass四维正畸临床病例分析沙龙第四期.mp4","associationFileId":134320866277300,"associationType":1,"category":1,"isDir":0,"pathId":19993,"size":0},{"associationFileName":"05_pass四维正畸临床病例分析沙龙第五期.mp4","associationFilePath":"/22000/【目录】PASS四维正畸临床病例分享/05_pass四维正畸临床病例分析沙龙第五期.mp4","associationFileId":584006493140984,"associationType":1,"category":1,"isDir":0,"pathId":19993,"size":0},{"associationFileName":"06_pass四维正畸临床病例分析沙龙第六期.mp4","associationFilePath":"/22000/【目录】PASS四维正畸临床病例分享/06_pass四维正畸临床病例分析沙龙第六期.mp4","associationFileId":71821886659071,"associationType":1,"category":1,"isDir":0,"pathId":19993,"size":0},{"associationFileName":"07_pass四维正畸临床病例分析沙龙第七期.mp4","associationFilePath":"/22000/【目录】PASS四维正畸临床病例分享/07_pass四维正畸临床病例分析沙龙第七期.mp4","associationFileId":661910111744364,"associationType":1,"category":1,"isDir":0,"pathId":19993,"size":0},{"associationFileName":"08_pass四维正畸临床病例分析沙龙第8期.mp4","associationFilePath":"/22000/【目录】PASS四维正畸临床病例分享/08_pass四维正畸临床病例分析沙龙第8期.mp4","associationFileId":450942519977592,"associationType":1,"category":1,"isDir":0,"pathId":19993,"size":0},{"associationFileName":"09_pass四维正畸临床病例分析沙龙第9期.mp4","associationFilePath":"/22000/【目录】PASS四维正畸临床病例分享/09_pass四维正畸临床病例分析沙龙第9期.mp4","associationFileId":723598626142219,"associationType":1,"category":1,"isDir":0,"pathId":19993,"size":0},{"associationFileName":"10_pass四维正畸临床病例分析沙龙第10期.mp4","associationFilePath":"/22000/【目录】PASS四维正畸临床病例分享/10_pass四维正畸临床病例分析沙龙第10期.mp4","associationFileId":599831031211518,"associationType":1,"category":1,"isDir":0,"pathId":19993,"size":0}],"more":false,"page":1,"pageSize":500}