{"data":[{"associationFileName":"01_《学员须知》.mp4","associationFilePath":"/2500/【目录】歌唱黄金知识点_精练歌曲【歌唱宝典】/01_《学员须知》.mp4","associationFileId":499600973874990,"associationType":1,"category":1,"isDir":0,"pathId":19794,"size":0},{"associationFileName":"02_1呼吸支持--歌唱的源动力（以《送别》为例讲解）.mp4","associationFilePath":"/2500/【目录】歌唱黄金知识点_精练歌曲【歌唱宝典】/02_1呼吸支持--歌唱的源动力（以《送别》为例讲解）.mp4","associationFileId":111408164741115,"associationType":1,"category":1,"isDir":0,"pathId":19794,"size":0},{"associationFileName":"03_2保持高位置--声音更具穿透力（以《绒花》为例讲解）.mp4","associationFilePath":"/2500/【目录】歌唱黄金知识点_精练歌曲【歌唱宝典】/03_2保持高位置--声音更具穿透力（以《绒花》为例讲解）.mp4","associationFileId":558619055264326,"associationType":1,"category":1,"isDir":0,"pathId":19794,"size":0},{"associationFileName":"04_3放松下巴--建立良好的歌唱状态（以《大海啊故乡》为例讲解）.mp4","associationFilePath":"/2500/【目录】歌唱黄金知识点_精练歌曲【歌唱宝典】/04_3放松下巴--建立良好的歌唱状态（以《大海啊故乡》为例讲解）.mp4","associationFileId":947433018851932,"associationType":1,"category":1,"isDir":0,"pathId":19794,"size":0},{"associationFileName":"05_4稳定喉头--助你轻松唱高音（以《我爱你塞北的雪》为例讲解）.mp4","associationFilePath":"/2500/【目录】歌唱黄金知识点_精练歌曲【歌唱宝典】/05_4稳定喉头--助你轻松唱高音（以《我爱你塞北的雪》为例讲解）.mp4","associationFileId":1016163816722376,"associationType":1,"category":1,"isDir":0,"pathId":19794,"size":0},{"associationFileName":"06_5声带闭合--解决漏气的关键（以《月亮花儿开》为例讲解）.mp4","associationFilePath":"/2500/【目录】歌唱黄金知识点_精练歌曲【歌唱宝典】/06_5声带闭合--解决漏气的关键（以《月亮花儿开》为例讲解）.mp4","associationFileId":298126016067376,"associationType":1,"category":1,"isDir":0,"pathId":19794,"size":0},{"associationFileName":"07_6抬起笑肌--漂亮音色的法宝（以《珊瑚颂》为例讲解）.mp4","associationFilePath":"/2500/【目录】歌唱黄金知识点_精练歌曲【歌唱宝典】/07_6抬起笑肌--漂亮音色的法宝（以《珊瑚颂》为例讲解）.mp4","associationFileId":833171955326255,"associationType":1,"category":1,"isDir":0,"pathId":19794,"size":0},{"associationFileName":"08_7运用共鸣腔体--“余音绕梁”的秘密（以《呼伦贝尔大草原》为例讲解）.mp4","associationFilePath":"/2500/【目录】歌唱黄金知识点_精练歌曲【歌唱宝典】/08_7运用共鸣腔体--“余音绕梁”的秘密（以《呼伦贝尔大草原》为例讲解）.mp4","associationFileId":988440002252668,"associationType":1,"category":1,"isDir":0,"pathId":19794,"size":0},{"associationFileName":"09_8打开通道--让声音上下自如（以《天边》为例讲解）.mp4","associationFilePath":"/2500/【目录】歌唱黄金知识点_精练歌曲【歌唱宝典】/09_8打开通道--让声音上下自如（以《天边》为例讲解）.mp4","associationFileId":519246413348577,"associationType":1,"category":1,"isDir":0,"pathId":19794,"size":0},{"associationFileName":"100_【专栏赠课】37《游牧时光》教唱(1).mp4","associationFilePath":"/2500/【目录】歌唱黄金知识点_精练歌曲【歌唱宝典】/100_【专栏赠课】37《游牧时光》教唱(1).mp4","associationFileId":368310328169282,"associationType":1,"category":1,"isDir":0,"pathId":19794,"size":0},{"associationFileName":"101_【专栏赠课】36《卓玛》教唱(2).mp4","associationFilePath":"/2500/【目录】歌唱黄金知识点_精练歌曲【歌唱宝典】/101_【专栏赠课】36《卓玛》教唱(2).mp4","associationFileId":189484286913167,"associationType":1,"category":1,"isDir":0,"pathId":19794,"size":0},{"associationFileName":"102_【专栏赠课】35《卓玛》教唱(1).mp4","associationFilePath":"/2500/【目录】歌唱黄金知识点_精练歌曲【歌唱宝典】/102_【专栏赠课】35《卓玛》教唱(1).mp4","associationFileId":35909289398301,"associationType":1,"category":1,"isDir":0,"pathId":19794,"size":0},{"associationFileName":"103_【专栏赠课】34《声声慢》教唱(2).mp4","associationFilePath":"/2500/【目录】歌唱黄金知识点_精练歌曲【歌唱宝典】/103_【专栏赠课】34《声声慢》教唱(2).mp4","associationFileId":768259313015409,"associationType":1,"category":1,"isDir":0,"pathId":19794,"size":0},{"associationFileName":"104_【专栏赠课】33《声声慢》教唱(1).mp4","associationFilePath":"/2500/【目录】歌唱黄金知识点_精练歌曲【歌唱宝典】/104_【专栏赠课】33《声声慢》教唱(1).mp4","associationFileId":138110330926,"associationType":1,"category":1,"isDir":0,"pathId":19794,"size":0},{"associationFileName":"105_【专栏赠课】32《天之大》教唱(2).mp4","associationFilePath":"/2500/【目录】歌唱黄金知识点_精练歌曲【歌唱宝典】/105_【专栏赠课】32《天之大》教唱(2).mp4","associationFileId":891750183310564,"associationType":1,"category":1,"isDir":0,"pathId":19794,"size":0},{"associationFileName":"106_【专栏赠课】31《天之大》教唱(1).mp4","associationFilePath":"/2500/【目录】歌唱黄金知识点_精练歌曲【歌唱宝典】/106_【专栏赠课】31《天之大》教唱(1).mp4","associationFileId":874404834828312,"associationType":1,"category":1,"isDir":0,"pathId":19794,"size":0},{"associationFileName":"107_【专栏赠课】30《红枣树》教唱(2).mp4","associationFilePath":"/2500/【目录】歌唱黄金知识点_精练歌曲【歌唱宝典】/107_【专栏赠课】30《红枣树》教唱(2).mp4","associationFileId":947647095680088,"associationType":1,"category":1,"isDir":0,"pathId":19794,"size":0},{"associationFileName":"108_【专栏赠课】29《红枣树》教唱(1).mp4","associationFilePath":"/2500/【目录】歌唱黄金知识点_精练歌曲【歌唱宝典】/108_【专栏赠课】29《红枣树》教唱(1).mp4","associationFileId":674923805823838,"associationType":1,"category":1,"isDir":0,"pathId":19794,"size":0},{"associationFileName":"109_【专栏赠课】28《今夜草原有雨》教唱(2).mp4","associationFilePath":"/2500/【目录】歌唱黄金知识点_精练歌曲【歌唱宝典】/109_【专栏赠课】28《今夜草原有雨》教唱(2).mp4","associationFileId":540395594300177,"associationType":1,"category":1,"isDir":0,"pathId":19794,"size":0},{"associationFileName":"10_9咬字发音--如何唱好中国作品（以《我和我的祖国》为例讲解）.mp4","associationFilePath":"/2500/【目录】歌唱黄金知识点_精练歌曲【歌唱宝典】/10_9咬字发音--如何唱好中国作品（以《我和我的祖国》为例讲解）.mp4","associationFileId":743245481198530,"associationType":1,"category":1,"isDir":0,"pathId":19794,"size":0},{"associationFileName":"110_【专栏赠课】27《今夜草原有雨》教唱(1).mp4","associationFilePath":"/2500/【目录】歌唱黄金知识点_精练歌曲【歌唱宝典】/110_【专栏赠课】27《今夜草原有雨》教唱(1).mp4","associationFileId":200108683457057,"associationType":1,"category":1,"isDir":0,"pathId":19794,"size":0},{"associationFileName":"111_【专栏赠课】26《呼伦贝尔大草原》教唱(2).mp4","associationFilePath":"/2500/【目录】歌唱黄金知识点_精练歌曲【歌唱宝典】/111_【专栏赠课】26《呼伦贝尔大草原》教唱(2).mp4","associationFileId":574426725925144,"associationType":1,"category":1,"isDir":0,"pathId":19794,"size":0},{"associationFileName":"112_【专栏赠课】25《呼伦贝尔大草原》教唱(1).mp4","associationFilePath":"/2500/【目录】歌唱黄金知识点_精练歌曲【歌唱宝典】/112_【专栏赠课】25《呼伦贝尔大草原》教唱(1).mp4","associationFileId":575555576499660,"associationType":1,"category":1,"isDir":0,"pathId":19794,"size":0},{"associationFileName":"113_【专栏赠课】24《梦中的额吉》教唱(2).mp4","associationFilePath":"/2500/【目录】歌唱黄金知识点_精练歌曲【歌唱宝典】/113_【专栏赠课】24《梦中的额吉》教唱(2).mp4","associationFileId":1091098673843333,"associationType":1,"category":1,"isDir":0,"pathId":19794,"size":0},{"associationFileName":"114_【专栏赠课】23《梦中的额吉》教唱(1).mp4","associationFilePath":"/2500/【目录】歌唱黄金知识点_精练歌曲【歌唱宝典】/114_【专栏赠课】23《梦中的额吉》教唱(1).mp4","associationFileId":149685480070808,"associationType":1,"category":1,"isDir":0,"pathId":19794,"size":0},{"associationFileName":"115_【专栏赠课】22《月夜》教唱.mp4","associationFilePath":"/2500/【目录】歌唱黄金知识点_精练歌曲【歌唱宝典】/115_【专栏赠课】22《月夜》教唱.mp4","associationFileId":560796208778569,"associationType":1,"category":1,"isDir":0,"pathId":19794,"size":0},{"associationFileName":"116_【专栏赠课】21《阿爸阿妈》教唱(2).mp4","associationFilePath":"/2500/【目录】歌唱黄金知识点_精练歌曲【歌唱宝典】/116_【专栏赠课】21《阿爸阿妈》教唱(2).mp4","associationFileId":616444963225179,"associationType":1,"category":1,"isDir":0,"pathId":19794,"size":0},{"associationFileName":"117_【专栏赠课】20《阿爸阿妈》教唱(1).mp4","associationFilePath":"/2500/【目录】歌唱黄金知识点_精练歌曲【歌唱宝典】/117_【专栏赠课】20《阿爸阿妈》教唱(1).mp4","associationFileId":620734073875872,"associationType":1,"category":1,"isDir":0,"pathId":19794,"size":0},{"associationFileName":"118_【专栏赠课】19《那拉提的养蜂女》教唱(2).mp4","associationFilePath":"/2500/【目录】歌唱黄金知识点_精练歌曲【歌唱宝典】/118_【专栏赠课】19《那拉提的养蜂女》教唱(2).mp4","associationFileId":164819782081919,"associationType":1,"category":1,"isDir":0,"pathId":19794,"size":0},{"associationFileName":"119_【专栏赠课】18《那拉提的养蜂女》教唱(1).mp4","associationFilePath":"/2500/【目录】歌唱黄金知识点_精练歌曲【歌唱宝典】/119_【专栏赠课】18《那拉提的养蜂女》教唱(1).mp4","associationFileId":182917067084963,"associationType":1,"category":1,"isDir":0,"pathId":19794,"size":0},{"associationFileName":"11_10建立音色库--演唱要因“歌”而异（以《九儿》为例讲解）.mp4","associationFilePath":"/2500/【目录】歌唱黄金知识点_精练歌曲【歌唱宝典】/11_10建立音色库--演唱要因“歌”而异（以《九儿》为例讲解）.mp4","associationFileId":822538284783665,"associationType":1,"category":1,"isDir":0,"pathId":19794,"size":0},{"associationFileName":"120_【专栏赠课】17《可可托海的牧羊人》《有缘人》教唱提升.mp4","associationFilePath":"/2500/【目录】歌唱黄金知识点_精练歌曲【歌唱宝典】/120_【专栏赠课】17《可可托海的牧羊人》《有缘人》教唱提升.mp4","associationFileId":1100971913204308,"associationType":1,"category":1,"isDir":0,"pathId":19794,"size":0},{"associationFileName":"121_【专栏赠课】16《可可托海的牧羊人》教唱(2).mp4","associationFilePath":"/2500/【目录】歌唱黄金知识点_精练歌曲【歌唱宝典】/121_【专栏赠课】16《可可托海的牧羊人》教唱(2).mp4","associationFileId":878890654429762,"associationType":1,"category":1,"isDir":0,"pathId":19794,"size":0},{"associationFileName":"122_【专栏赠课】15《可可托海的牧羊人》教唱(1).mp4","associationFilePath":"/2500/【目录】歌唱黄金知识点_精练歌曲【歌唱宝典】/122_【专栏赠课】15《可可托海的牧羊人》教唱(1).mp4","associationFileId":177402153205431,"associationType":1,"category":1,"isDir":0,"pathId":19794,"size":0},{"associationFileName":"123_【专栏赠课】14《有缘人》教唱.mp4","associationFilePath":"/2500/【目录】歌唱黄金知识点_精练歌曲【歌唱宝典】/123_【专栏赠课】14《有缘人》教唱.mp4","associationFileId":476003671982886,"associationType":1,"category":1,"isDir":0,"pathId":19794,"size":0},{"associationFileName":"124_【专栏赠课】13《梅花泪》教唱.mp4","associationFilePath":"/2500/【目录】歌唱黄金知识点_精练歌曲【歌唱宝典】/124_【专栏赠课】13《梅花泪》教唱.mp4","associationFileId":377542926894828,"associationType":1,"category":1,"isDir":0,"pathId":19794,"size":0},{"associationFileName":"125_【专栏赠课】12《美人吟》教唱(2).mp4","associationFilePath":"/2500/【目录】歌唱黄金知识点_精练歌曲【歌唱宝典】/125_【专栏赠课】12《美人吟》教唱(2).mp4","associationFileId":1028065122454101,"associationType":1,"category":1,"isDir":0,"pathId":19794,"size":0},{"associationFileName":"126_【专栏赠课】11《美人吟》教唱(1).mp4","associationFilePath":"/2500/【目录】歌唱黄金知识点_精练歌曲【歌唱宝典】/126_【专栏赠课】11《美人吟》教唱(1).mp4","associationFileId":270337743149203,"associationType":1,"category":1,"isDir":0,"pathId":19794,"size":0},{"associationFileName":"127_【专栏赠课】10《红唇》教唱(2).mp4","associationFilePath":"/2500/【目录】歌唱黄金知识点_精练歌曲【歌唱宝典】/127_【专栏赠课】10《红唇》教唱(2).mp4","associationFileId":797788462970206,"associationType":1,"category":1,"isDir":0,"pathId":19794,"size":0},{"associationFileName":"128_【专栏赠课】9《红唇》教唱(1).mp4","associationFilePath":"/2500/【目录】歌唱黄金知识点_精练歌曲【歌唱宝典】/128_【专栏赠课】9《红唇》教唱(1).mp4","associationFileId":1072147980864308,"associationType":1,"category":1,"isDir":0,"pathId":19794,"size":0},{"associationFileName":"129_【专栏赠课】8《最亲的人》教唱(2).mp4","associationFilePath":"/2500/【目录】歌唱黄金知识点_精练歌曲【歌唱宝典】/129_【专栏赠课】8《最亲的人》教唱(2).mp4","associationFileId":871148473183242,"associationType":1,"category":1,"isDir":0,"pathId":19794,"size":0},{"associationFileName":"12_11声情并茂--歌唱的表情与动作（以《我是一条小河》为例讲解）.mp4","associationFilePath":"/2500/【目录】歌唱黄金知识点_精练歌曲【歌唱宝典】/12_11声情并茂--歌唱的表情与动作（以《我是一条小河》为例讲解）.mp4","associationFileId":360889771767205,"associationType":1,"category":1,"isDir":0,"pathId":19794,"size":0},{"associationFileName":"130_【专栏赠课】7《最亲的人》教唱(1).mp4","associationFilePath":"/2500/【目录】歌唱黄金知识点_精练歌曲【歌唱宝典】/130_【专栏赠课】7《最亲的人》教唱(1).mp4","associationFileId":1041278922687902,"associationType":1,"category":1,"isDir":0,"pathId":19794,"size":0},{"associationFileName":"131_【专栏赠课】6《我是一条小河》教唱.mp4","associationFilePath":"/2500/【目录】歌唱黄金知识点_精练歌曲【歌唱宝典】/131_【专栏赠课】6《我是一条小河》教唱.mp4","associationFileId":367749445958928,"associationType":1,"category":1,"isDir":0,"pathId":19794,"size":0},{"associationFileName":"132_【专栏赠课】5《陪你一起看草原》教唱(2).mp4","associationFilePath":"/2500/【目录】歌唱黄金知识点_精练歌曲【歌唱宝典】/132_【专栏赠课】5《陪你一起看草原》教唱(2).mp4","associationFileId":264206319629938,"associationType":1,"category":1,"isDir":0,"pathId":19794,"size":0},{"associationFileName":"133_【专栏赠课】4《陪你一起看草原》教唱(1).mp4","associationFilePath":"/2500/【目录】歌唱黄金知识点_精练歌曲【歌唱宝典】/133_【专栏赠课】4《陪你一起看草原》教唱(1).mp4","associationFileId":803225287184322,"associationType":1,"category":1,"isDir":0,"pathId":19794,"size":0},{"associationFileName":"134_【专栏赠课】3《心上的罗加》教唱.mp4","associationFilePath":"/2500/【目录】歌唱黄金知识点_精练歌曲【歌唱宝典】/134_【专栏赠课】3《心上的罗加》教唱.mp4","associationFileId":387781774658269,"associationType":1,"category":1,"isDir":0,"pathId":19794,"size":0},{"associationFileName":"135_【专栏赠课】2《万事如意》教唱(2).mp4","associationFilePath":"/2500/【目录】歌唱黄金知识点_精练歌曲【歌唱宝典】/135_【专栏赠课】2《万事如意》教唱(2).mp4","associationFileId":661062194504078,"associationType":1,"category":1,"isDir":0,"pathId":19794,"size":0},{"associationFileName":"136_【专栏赠课】1《万事如意》教唱(1).mp4","associationFilePath":"/2500/【目录】歌唱黄金知识点_精练歌曲【歌唱宝典】/136_【专栏赠课】1《万事如意》教唱(1).mp4","associationFileId":534720670362345,"associationType":1,"category":1,"isDir":0,"pathId":19794,"size":0},{"associationFileName":"137_双十一特惠大促，学员互动点评课.mp4","associationFilePath":"/2500/【目录】歌唱黄金知识点_精练歌曲【歌唱宝典】/137_双十一特惠大促，学员互动点评课.mp4","associationFileId":77087255516412,"associationType":1,"category":1,"isDir":0,"pathId":19794,"size":0},{"associationFileName":"138_【专栏赠课】113《心上人》教唱.mp4","associationFilePath":"/2500/【目录】歌唱黄金知识点_精练歌曲【歌唱宝典】/138_【专栏赠课】113《心上人》教唱.mp4","associationFileId":882806008886814,"associationType":1,"category":1,"isDir":0,"pathId":19794,"size":0},{"associationFileName":"139_【专栏赠课】114《想问情深有几许》教唱.mp4","associationFilePath":"/2500/【目录】歌唱黄金知识点_精练歌曲【歌唱宝典】/139_【专栏赠课】114《想问情深有几许》教唱.mp4","associationFileId":841192508059484,"associationType":1,"category":1,"isDir":0,"pathId":19794,"size":0},{"associationFileName":"13_1草原风格歌曲《父亲的草原母亲的河》双十二特惠福利.mp4","associationFilePath":"/2500/【目录】歌唱黄金知识点_精练歌曲【歌唱宝典】/13_1草原风格歌曲《父亲的草原母亲的河》双十二特惠福利.mp4","associationFileId":320786920818783,"associationType":1,"category":1,"isDir":0,"pathId":19794,"size":0},{"associationFileName":"140_【专栏赠课】115《妈妈的手》教唱.mp4","associationFilePath":"/2500/【目录】歌唱黄金知识点_精练歌曲【歌唱宝典】/140_【专栏赠课】115《妈妈的手》教唱.mp4","associationFileId":476967847485487,"associationType":1,"category":1,"isDir":0,"pathId":19794,"size":0},{"associationFileName":"141_【专栏赠课】116《微风细雨》教唱.mp4","associationFilePath":"/2500/【目录】歌唱黄金知识点_精练歌曲【歌唱宝典】/141_【专栏赠课】116《微风细雨》教唱.mp4","associationFileId":547942955671943,"associationType":1,"category":1,"isDir":0,"pathId":19794,"size":0},{"associationFileName":"142_【专栏赠课】117《今生我在修佛缘》教唱.mp4","associationFilePath":"/2500/【目录】歌唱黄金知识点_精练歌曲【歌唱宝典】/142_【专栏赠课】117《今生我在修佛缘》教唱.mp4","associationFileId":944865871648625,"associationType":1,"category":1,"isDir":0,"pathId":19794,"size":0},{"associationFileName":"143_【专栏赠课】118《天上的海》教唱.mp4","associationFilePath":"/2500/【目录】歌唱黄金知识点_精练歌曲【歌唱宝典】/143_【专栏赠课】118《天上的海》教唱.mp4","associationFileId":850056754968492,"associationType":1,"category":1,"isDir":0,"pathId":19794,"size":0},{"associationFileName":"144_【专栏赠课】119《乌兰巴托的夜》.mp4","associationFilePath":"/2500/【目录】歌唱黄金知识点_精练歌曲【歌唱宝典】/144_【专栏赠课】119《乌兰巴托的夜》.mp4","associationFileId":462754634246329,"associationType":1,"category":1,"isDir":0,"pathId":19794,"size":0},{"associationFileName":"145_【专栏赠课】120《花妖》.mp4","associationFilePath":"/2500/【目录】歌唱黄金知识点_精练歌曲【歌唱宝典】/145_【专栏赠课】120《花妖》.mp4","associationFileId":1035225588347486,"associationType":1,"category":1,"isDir":0,"pathId":19794,"size":0},{"associationFileName":"146_【专栏赠课】121《如是》教唱.mp4","associationFilePath":"/2500/【目录】歌唱黄金知识点_精练歌曲【歌唱宝典】/146_【专栏赠课】121《如是》教唱.mp4","associationFileId":799077260133487,"associationType":1,"category":1,"isDir":0,"pathId":19794,"size":0},{"associationFileName":"14_2爱国主旋律歌曲《我爱你中国》.mp4","associationFilePath":"/2500/【目录】歌唱黄金知识点_精练歌曲【歌唱宝典】/14_2爱国主旋律歌曲《我爱你中国》.mp4","associationFileId":88569017673923,"associationType":1,"category":1,"isDir":0,"pathId":19794,"size":0},{"associationFileName":"15_3流行通俗歌曲《可可托海的牧羊人》.mp4","associationFilePath":"/2500/【目录】歌唱黄金知识点_精练歌曲【歌唱宝典】/15_3流行通俗歌曲《可可托海的牧羊人》.mp4","associationFileId":1097774743411345,"associationType":1,"category":1,"isDir":0,"pathId":19794,"size":0},{"associationFileName":"16_4民族通俗歌曲《康美之恋》.mp4","associationFilePath":"/2500/【目录】歌唱黄金知识点_精练歌曲【歌唱宝典】/16_4民族通俗歌曲《康美之恋》.mp4","associationFileId":367454062290830,"associationType":1,"category":1,"isDir":0,"pathId":19794,"size":0},{"associationFileName":"17_5情感主题歌曲《人间第一情》.mp4","associationFilePath":"/2500/【目录】歌唱黄金知识点_精练歌曲【歌唱宝典】/17_5情感主题歌曲《人间第一情》.mp4","associationFileId":297478575679922,"associationType":1,"category":1,"isDir":0,"pathId":19794,"size":0},{"associationFileName":"18_6军旅素材歌曲《军人本色》.mp4","associationFilePath":"/2500/【目录】歌唱黄金知识点_精练歌曲【歌唱宝典】/18_6军旅素材歌曲《军人本色》.mp4","associationFileId":76500149478653,"associationType":1,"category":1,"isDir":0,"pathId":19794,"size":0},{"associationFileName":"19_7地方民歌歌曲《一杯美酒》.mp4","associationFilePath":"/2500/【目录】歌唱黄金知识点_精练歌曲【歌唱宝典】/19_7地方民歌歌曲《一杯美酒》.mp4","associationFileId":244749375420959,"associationType":1,"category":1,"isDir":0,"pathId":19794,"size":0},{"associationFileName":"20_8京戏元素歌曲《前门情思大碗茶》.mp4","associationFilePath":"/2500/【目录】歌唱黄金知识点_精练歌曲【歌唱宝典】/20_8京戏元素歌曲《前门情思大碗茶》.mp4","associationFileId":958126699634465,"associationType":1,"category":1,"isDir":0,"pathId":19794,"size":0},{"associationFileName":"21_9古诗词歌曲《红豆词》.mp4","associationFilePath":"/2500/【目录】歌唱黄金知识点_精练歌曲【歌唱宝典】/21_9古诗词歌曲《红豆词》.mp4","associationFileId":34559973759610,"associationType":1,"category":1,"isDir":0,"pathId":19794,"size":0},{"associationFileName":"22_10中国艺术歌曲《玫瑰三愿》.mp4","associationFilePath":"/2500/【目录】歌唱黄金知识点_精练歌曲【歌唱宝典】/22_10中国艺术歌曲《玫瑰三愿》.mp4","associationFileId":552139380061772,"associationType":1,"category":1,"isDir":0,"pathId":19794,"size":0},{"associationFileName":"23_11花腔咏叹歌曲《七月的草原》.mp4","associationFilePath":"/2500/【目录】歌唱黄金知识点_精练歌曲【歌唱宝典】/23_11花腔咏叹歌曲《七月的草原》.mp4","associationFileId":310462975428364,"associationType":1,"category":1,"isDir":0,"pathId":19794,"size":0},{"associationFileName":"24_【专栏赠课】112《为你祈祷》教唱.mp4","associationFilePath":"/2500/【目录】歌唱黄金知识点_精练歌曲【歌唱宝典】/24_【专栏赠课】112《为你祈祷》教唱.mp4","associationFileId":880985289833857,"associationType":1,"category":1,"isDir":0,"pathId":19794,"size":0},{"associationFileName":"25_【专栏赠课】111《烟雨唱扬州》教唱.mp4","associationFilePath":"/2500/【目录】歌唱黄金知识点_精练歌曲【歌唱宝典】/25_【专栏赠课】111《烟雨唱扬州》教唱.mp4","associationFileId":571677861063975,"associationType":1,"category":1,"isDir":0,"pathId":19794,"size":0},{"associationFileName":"26_【专栏赠课】110《一半疯了一半算了》教唱.mp4","associationFilePath":"/2500/【目录】歌唱黄金知识点_精练歌曲【歌唱宝典】/26_【专栏赠课】110《一半疯了一半算了》教唱.mp4","associationFileId":418106697031733,"associationType":1,"category":1,"isDir":0,"pathId":19794,"size":0},{"associationFileName":"27_【专栏赠课】109《女人花》教唱.mp4","associationFilePath":"/2500/【目录】歌唱黄金知识点_精练歌曲【歌唱宝典】/27_【专栏赠课】109《女人花》教唱.mp4","associationFileId":592681428959123,"associationType":1,"category":1,"isDir":0,"pathId":19794,"size":0},{"associationFileName":"28_【专栏赠课】108《花桥流水》教唱.mp4","associationFilePath":"/2500/【目录】歌唱黄金知识点_精练歌曲【歌唱宝典】/28_【专栏赠课】108《花桥流水》教唱.mp4","associationFileId":696458837831965,"associationType":1,"category":1,"isDir":0,"pathId":19794,"size":0},{"associationFileName":"29_【专栏赠课】107《早安隆回》教唱.mp4","associationFilePath":"/2500/【目录】歌唱黄金知识点_精练歌曲【歌唱宝典】/29_【专栏赠课】107《早安隆回》教唱.mp4","associationFileId":114248330159795,"associationType":1,"category":1,"isDir":0,"pathId":19794,"size":0},{"associationFileName":"30_【专栏赠课】106《爱随浪花漂去远方》教唱.mp4","associationFilePath":"/2500/【目录】歌唱黄金知识点_精练歌曲【歌唱宝典】/30_【专栏赠课】106《爱随浪花漂去远方》教唱.mp4","associationFileId":339407013598875,"associationType":1,"category":1,"isDir":0,"pathId":19794,"size":0},{"associationFileName":"31_【专栏赠课】105《我来人间一趟》教唱.mp4","associationFilePath":"/2500/【目录】歌唱黄金知识点_精练歌曲【歌唱宝典】/31_【专栏赠课】105《我来人间一趟》教唱.mp4","associationFileId":429525247640050,"associationType":1,"category":1,"isDir":0,"pathId":19794,"size":0},{"associationFileName":"32_【专栏赠课】104《如水年华》教唱.mp4","associationFilePath":"/2500/【目录】歌唱黄金知识点_精练歌曲【歌唱宝典】/32_【专栏赠课】104《如水年华》教唱.mp4","associationFileId":872254234322847,"associationType":1,"category":1,"isDir":0,"pathId":19794,"size":0},{"associationFileName":"33_【专栏赠课】103《不是孤雁》教唱.mp4","associationFilePath":"/2500/【目录】歌唱黄金知识点_精练歌曲【歌唱宝典】/33_【专栏赠课】103《不是孤雁》教唱.mp4","associationFileId":89357854003474,"associationType":1,"category":1,"isDir":0,"pathId":19794,"size":0},{"associationFileName":"34_【专栏赠课】102《相思月》教唱.mp4","associationFilePath":"/2500/【目录】歌唱黄金知识点_精练歌曲【歌唱宝典】/34_【专栏赠课】102《相思月》教唱.mp4","associationFileId":66344724752653,"associationType":1,"category":1,"isDir":0,"pathId":19794,"size":0},{"associationFileName":"35_【专栏赠课】101《那一天》教唱.mp4","associationFilePath":"/2500/【目录】歌唱黄金知识点_精练歌曲【歌唱宝典】/35_【专栏赠课】101《那一天》教唱.mp4","associationFileId":708939260303894,"associationType":1,"category":1,"isDir":0,"pathId":19794,"size":0},{"associationFileName":"36_【专栏赠课】100《望月》教唱.mp4","associationFilePath":"/2500/【目录】歌唱黄金知识点_精练歌曲【歌唱宝典】/36_【专栏赠课】100《望月》教唱.mp4","associationFileId":383514023643305,"associationType":1,"category":1,"isDir":0,"pathId":19794,"size":0},{"associationFileName":"37_【专栏赠课】99《你》教唱.mp4","associationFilePath":"/2500/【目录】歌唱黄金知识点_精练歌曲【歌唱宝典】/37_【专栏赠课】99《你》教唱.mp4","associationFileId":384205004689128,"associationType":1,"category":1,"isDir":0,"pathId":19794,"size":0},{"associationFileName":"38_【专栏赠课】98《我是你的格桑花》教唱.mp4","associationFilePath":"/2500/【目录】歌唱黄金知识点_精练歌曲【歌唱宝典】/38_【专栏赠课】98《我是你的格桑花》教唱.mp4","associationFileId":396952558179043,"associationType":1,"category":1,"isDir":0,"pathId":19794,"size":0},{"associationFileName":"39_【专栏赠课】97《为你等待》教唱.mp4","associationFilePath":"/2500/【目录】歌唱黄金知识点_精练歌曲【歌唱宝典】/39_【专栏赠课】97《为你等待》教唱.mp4","associationFileId":253611998834216,"associationType":1,"category":1,"isDir":0,"pathId":19794,"size":0},{"associationFileName":"40_【专栏赠课】96《伤疤还没好就忘了疼》教唱.mp4","associationFilePath":"/2500/【目录】歌唱黄金知识点_精练歌曲【歌唱宝典】/40_【专栏赠课】96《伤疤还没好就忘了疼》教唱.mp4","associationFileId":972691383944967,"associationType":1,"category":1,"isDir":0,"pathId":19794,"size":0},{"associationFileName":"41_【专栏赠课】95《苍天的孩子》教唱.mp4","associationFilePath":"/2500/【目录】歌唱黄金知识点_精练歌曲【歌唱宝典】/41_【专栏赠课】95《苍天的孩子》教唱.mp4","associationFileId":874509180378687,"associationType":1,"category":1,"isDir":0,"pathId":19794,"size":0},{"associationFileName":"42_【专栏赠课】94《爱在羊茸山水间》教唱.mp4","associationFilePath":"/2500/【目录】歌唱黄金知识点_精练歌曲【歌唱宝典】/42_【专栏赠课】94《爱在羊茸山水间》教唱.mp4","associationFileId":1065367653166592,"associationType":1,"category":1,"isDir":0,"pathId":19794,"size":0},{"associationFileName":"43_【专栏赠课】93《旧梦》教唱.mp4","associationFilePath":"/2500/【目录】歌唱黄金知识点_精练歌曲【歌唱宝典】/43_【专栏赠课】93《旧梦》教唱.mp4","associationFileId":905466396953689,"associationType":1,"category":1,"isDir":0,"pathId":19794,"size":0},{"associationFileName":"44_【专栏赠课】92《传奇》教唱.mp4","associationFilePath":"/2500/【目录】歌唱黄金知识点_精练歌曲【歌唱宝典】/44_【专栏赠课】92《传奇》教唱.mp4","associationFileId":84538125865262,"associationType":1,"category":1,"isDir":0,"pathId":19794,"size":0},{"associationFileName":"45_【专栏赠课】91《天边的月亮》教唱.mp4","associationFilePath":"/2500/【目录】歌唱黄金知识点_精练歌曲【歌唱宝典】/45_【专栏赠课】91《天边的月亮》教唱.mp4","associationFileId":1061165997783504,"associationType":1,"category":1,"isDir":0,"pathId":19794,"size":0},{"associationFileName":"46_【专栏赠课】90《神奇草原》教唱.mp4","associationFilePath":"/2500/【目录】歌唱黄金知识点_精练歌曲【歌唱宝典】/46_【专栏赠课】90《神奇草原》教唱.mp4","associationFileId":306574180691877,"associationType":1,"category":1,"isDir":0,"pathId":19794,"size":0},{"associationFileName":"47_【专栏赠课】89《三生石下》教唱.mp4","associationFilePath":"/2500/【目录】歌唱黄金知识点_精练歌曲【歌唱宝典】/47_【专栏赠课】89《三生石下》教唱.mp4","associationFileId":761143800843670,"associationType":1,"category":1,"isDir":0,"pathId":19794,"size":0},{"associationFileName":"48_【专栏赠课】88《太想念》教唱.mp4","associationFilePath":"/2500/【目录】歌唱黄金知识点_精练歌曲【歌唱宝典】/48_【专栏赠课】88《太想念》教唱.mp4","associationFileId":623763398909111,"associationType":1,"category":1,"isDir":0,"pathId":19794,"size":0},{"associationFileName":"49_【专栏赠课】87《还没有爱够》教唱.mp4","associationFilePath":"/2500/【目录】歌唱黄金知识点_精练歌曲【歌唱宝典】/49_【专栏赠课】87《还没有爱够》教唱.mp4","associationFileId":924204015500240,"associationType":1,"category":1,"isDir":0,"pathId":19794,"size":0},{"associationFileName":"50_【专栏赠课】86《胡琴说》教唱.mp4","associationFilePath":"/2500/【目录】歌唱黄金知识点_精练歌曲【歌唱宝典】/50_【专栏赠课】86《胡琴说》教唱.mp4","associationFileId":709609187451133,"associationType":1,"category":1,"isDir":0,"pathId":19794,"size":0},{"associationFileName":"51_【专栏赠课】85《我的情深你若懂》教唱.mp4","associationFilePath":"/2500/【目录】歌唱黄金知识点_精练歌曲【歌唱宝典】/51_【专栏赠课】85《我的情深你若懂》教唱.mp4","associationFileId":980544944953016,"associationType":1,"category":1,"isDir":0,"pathId":19794,"size":0},{"associationFileName":"52_【专栏赠课】84《家乡的月亮》教唱.mp4","associationFilePath":"/2500/【目录】歌唱黄金知识点_精练歌曲【歌唱宝典】/52_【专栏赠课】84《家乡的月亮》教唱.mp4","associationFileId":552067584095197,"associationType":1,"category":1,"isDir":0,"pathId":19794,"size":0},{"associationFileName":"53_【专栏赠课】83《有生之恋》教唱.mp4","associationFilePath":"/2500/【目录】歌唱黄金知识点_精练歌曲【歌唱宝典】/53_【专栏赠课】83《有生之恋》教唱.mp4","associationFileId":680677804921554,"associationType":1,"category":1,"isDir":0,"pathId":19794,"size":0},{"associationFileName":"54_【专栏赠课】82《画你》教唱.mp4","associationFilePath":"/2500/【目录】歌唱黄金知识点_精练歌曲【歌唱宝典】/54_【专栏赠课】82《画你》教唱.mp4","associationFileId":763309554012375,"associationType":1,"category":1,"isDir":0,"pathId":19794,"size":0},{"associationFileName":"55_【专栏赠课】81《女人》教唱.mp4","associationFilePath":"/2500/【目录】歌唱黄金知识点_精练歌曲【歌唱宝典】/55_【专栏赠课】81《女人》教唱.mp4","associationFileId":81088377087772,"associationType":1,"category":1,"isDir":0,"pathId":19794,"size":0},{"associationFileName":"56_【专栏赠课】80《成都》教唱.mp4","associationFilePath":"/2500/【目录】歌唱黄金知识点_精练歌曲【歌唱宝典】/56_【专栏赠课】80《成都》教唱.mp4","associationFileId":1333752149307,"associationType":1,"category":1,"isDir":0,"pathId":19794,"size":0},{"associationFileName":"57_【专栏赠课】79《一曲红尘》教唱.mp4","associationFilePath":"/2500/【目录】歌唱黄金知识点_精练歌曲【歌唱宝典】/57_【专栏赠课】79《一曲红尘》教唱.mp4","associationFileId":657709180995758,"associationType":1,"category":1,"isDir":0,"pathId":19794,"size":0},{"associationFileName":"58_【专栏赠课】78《半壶纱》教唱.mp4","associationFilePath":"/2500/【目录】歌唱黄金知识点_精练歌曲【歌唱宝典】/58_【专栏赠课】78《半壶纱》教唱.mp4","associationFileId":6505769803275,"associationType":1,"category":1,"isDir":0,"pathId":19794,"size":0},{"associationFileName":"59_【专栏赠课】77《这世界那么多人》教唱.mp4","associationFilePath":"/2500/【目录】歌唱黄金知识点_精练歌曲【歌唱宝典】/59_【专栏赠课】77《这世界那么多人》教唱.mp4","associationFileId":829622735741583,"associationType":1,"category":1,"isDir":0,"pathId":19794,"size":0},{"associationFileName":"60_【专栏赠课】76《好运来》教唱.mp4","associationFilePath":"/2500/【目录】歌唱黄金知识点_精练歌曲【歌唱宝典】/60_【专栏赠课】76《好运来》教唱.mp4","associationFileId":344619133450623,"associationType":1,"category":1,"isDir":0,"pathId":19794,"size":0},{"associationFileName":"61_【专栏赠课】75《醉乡》教唱.mp4","associationFilePath":"/2500/【目录】歌唱黄金知识点_精练歌曲【歌唱宝典】/61_【专栏赠课】75《醉乡》教唱.mp4","associationFileId":5156403462217,"associationType":1,"category":1,"isDir":0,"pathId":19794,"size":0},{"associationFileName":"62_【专栏赠课】74《最远的你是我最近的爱》教唱.mp4","associationFilePath":"/2500/【目录】歌唱黄金知识点_精练歌曲【歌唱宝典】/62_【专栏赠课】74《最远的你是我最近的爱》教唱.mp4","associationFileId":361358551399870,"associationType":1,"category":1,"isDir":0,"pathId":19794,"size":0},{"associationFileName":"63_【专栏赠课】73《女儿情》教唱.mp4","associationFilePath":"/2500/【目录】歌唱黄金知识点_精练歌曲【歌唱宝典】/63_【专栏赠课】73《女儿情》教唱.mp4","associationFileId":262745776928876,"associationType":1,"category":1,"isDir":0,"pathId":19794,"size":0},{"associationFileName":"64_【专栏赠课】72《靖远之恋》教唱.mp4","associationFilePath":"/2500/【目录】歌唱黄金知识点_精练歌曲【歌唱宝典】/64_【专栏赠课】72《靖远之恋》教唱.mp4","associationFileId":61271687004571,"associationType":1,"category":1,"isDir":0,"pathId":19794,"size":0},{"associationFileName":"65_【专栏赠课】71《听闻远方有你》教唱.mp4","associationFilePath":"/2500/【目录】歌唱黄金知识点_精练歌曲【歌唱宝典】/65_【专栏赠课】71《听闻远方有你》教唱.mp4","associationFileId":12306106047131,"associationType":1,"category":1,"isDir":0,"pathId":19794,"size":0},{"associationFileName":"66_【专栏赠课】70《想着你亲爱的》教唱.mp4","associationFilePath":"/2500/【目录】歌唱黄金知识点_精练歌曲【歌唱宝典】/66_【专栏赠课】70《想着你亲爱的》教唱.mp4","associationFileId":163303150537471,"associationType":1,"category":1,"isDir":0,"pathId":19794,"size":0},{"associationFileName":"67_【专栏赠课】69《往事只能回味》教唱.mp4","associationFilePath":"/2500/【目录】歌唱黄金知识点_精练歌曲【歌唱宝典】/67_【专栏赠课】69《往事只能回味》教唱.mp4","associationFileId":366611136195267,"associationType":1,"category":1,"isDir":0,"pathId":19794,"size":0},{"associationFileName":"68_【专栏赠课】68《惜别的海岸》教唱.mp4","associationFilePath":"/2500/【目录】歌唱黄金知识点_精练歌曲【歌唱宝典】/68_【专栏赠课】68《惜别的海岸》教唱.mp4","associationFileId":878578846839608,"associationType":1,"category":1,"isDir":0,"pathId":19794,"size":0},{"associationFileName":"69_双11大促“课程二合一”公益声乐课.mp4","associationFilePath":"/2500/【目录】歌唱黄金知识点_精练歌曲【歌唱宝典】/69_双11大促“课程二合一”公益声乐课.mp4","associationFileId":640729003387085,"associationType":1,"category":1,"isDir":0,"pathId":19794,"size":0},{"associationFileName":"70_【专栏赠课】67《绿色背影》教唱.mp4","associationFilePath":"/2500/【目录】歌唱黄金知识点_精练歌曲【歌唱宝典】/70_【专栏赠课】67《绿色背影》教唱.mp4","associationFileId":854796652908695,"associationType":1,"category":1,"isDir":0,"pathId":19794,"size":0},{"associationFileName":"71_【专栏赠课】66《城里的月光》教唱.mp4","associationFilePath":"/2500/【目录】歌唱黄金知识点_精练歌曲【歌唱宝典】/71_【专栏赠课】66《城里的月光》教唱.mp4","associationFileId":650687986806125,"associationType":1,"category":1,"isDir":0,"pathId":19794,"size":0},{"associationFileName":"72_【专栏赠课】65《伤心的酒吧》教唱.mp4","associationFilePath":"/2500/【目录】歌唱黄金知识点_精练歌曲【歌唱宝典】/72_【专栏赠课】65《伤心的酒吧》教唱.mp4","associationFileId":596230908766287,"associationType":1,"category":1,"isDir":0,"pathId":19794,"size":0},{"associationFileName":"73_【专栏赠课】64《明月夜》教唱.mp4","associationFilePath":"/2500/【目录】歌唱黄金知识点_精练歌曲【歌唱宝典】/73_【专栏赠课】64《明月夜》教唱.mp4","associationFileId":814735992764719,"associationType":1,"category":1,"isDir":0,"pathId":19794,"size":0},{"associationFileName":"74_【专栏赠课】63《别知己》教唱.mp4","associationFilePath":"/2500/【目录】歌唱黄金知识点_精练歌曲【歌唱宝典】/74_【专栏赠课】63《别知己》教唱.mp4","associationFileId":531958280483330,"associationType":1,"category":1,"isDir":0,"pathId":19794,"size":0},{"associationFileName":"75_【专栏赠课】62《今天是你的生日》教唱.mp4","associationFilePath":"/2500/【目录】歌唱黄金知识点_精练歌曲【歌唱宝典】/75_【专栏赠课】62《今天是你的生日》教唱.mp4","associationFileId":1052196254447723,"associationType":1,"category":1,"isDir":0,"pathId":19794,"size":0},{"associationFileName":"76_【专栏赠送】61《听心》教唱.mp4","associationFilePath":"/2500/【目录】歌唱黄金知识点_精练歌曲【歌唱宝典】/76_【专栏赠送】61《听心》教唱.mp4","associationFileId":288078568523384,"associationType":1,"category":1,"isDir":0,"pathId":19794,"size":0},{"associationFileName":"77_【专栏赠课】60《次真拉姆》教唱(2).mp4","associationFilePath":"/2500/【目录】歌唱黄金知识点_精练歌曲【歌唱宝典】/77_【专栏赠课】60《次真拉姆》教唱(2).mp4","associationFileId":349653091130194,"associationType":1,"category":1,"isDir":0,"pathId":19794,"size":0},{"associationFileName":"78_【专栏赠课】59《次真拉姆》教唱(1).mp4","associationFilePath":"/2500/【目录】歌唱黄金知识点_精练歌曲【歌唱宝典】/78_【专栏赠课】59《次真拉姆》教唱(1).mp4","associationFileId":372907528931377,"associationType":1,"category":1,"isDir":0,"pathId":19794,"size":0},{"associationFileName":"79_【专栏赠课】58《今夜无眠》教唱(2).mp4","associationFilePath":"/2500/【目录】歌唱黄金知识点_精练歌曲【歌唱宝典】/79_【专栏赠课】58《今夜无眠》教唱(2).mp4","associationFileId":448179794368817,"associationType":1,"category":1,"isDir":0,"pathId":19794,"size":0},{"associationFileName":"80_【专栏赠课】57《今夜无眠》教唱(1).mp4","associationFilePath":"/2500/【目录】歌唱黄金知识点_精练歌曲【歌唱宝典】/80_【专栏赠课】57《今夜无眠》教唱(1).mp4","associationFileId":911512859522124,"associationType":1,"category":1,"isDir":0,"pathId":19794,"size":0},{"associationFileName":"81_【专栏赠课】56《又见山里红》教唱(2).mp4","associationFilePath":"/2500/【目录】歌唱黄金知识点_精练歌曲【歌唱宝典】/81_【专栏赠课】56《又见山里红》教唱(2).mp4","associationFileId":532108587693643,"associationType":1,"category":1,"isDir":0,"pathId":19794,"size":0},{"associationFileName":"82_【专栏赠课】55《又见山里红》教唱(1).mp4","associationFilePath":"/2500/【目录】歌唱黄金知识点_精练歌曲【歌唱宝典】/82_【专栏赠课】55《又见山里红》教唱(1).mp4","associationFileId":677723562189619,"associationType":1,"category":1,"isDir":0,"pathId":19794,"size":0},{"associationFileName":"83_【专栏赠课】《如果爱还在》教唱(2).mp4","associationFilePath":"/2500/【目录】歌唱黄金知识点_精练歌曲【歌唱宝典】/83_【专栏赠课】《如果爱还在》教唱(2).mp4","associationFileId":746243870085856,"associationType":1,"category":1,"isDir":0,"pathId":19794,"size":0},{"associationFileName":"84_【专栏赠课】54《如果爱还在》教唱(1).mp4","associationFilePath":"/2500/【目录】歌唱黄金知识点_精练歌曲【歌唱宝典】/84_【专栏赠课】54《如果爱还在》教唱(1).mp4","associationFileId":834850808575630,"associationType":1,"category":1,"isDir":0,"pathId":19794,"size":0},{"associationFileName":"85_【专栏赠课】53《想你的时候问月亮》教唱(2).mp4","associationFilePath":"/2500/【目录】歌唱黄金知识点_精练歌曲【歌唱宝典】/85_【专栏赠课】53《想你的时候问月亮》教唱(2).mp4","associationFileId":28442196177575,"associationType":1,"category":1,"isDir":0,"pathId":19794,"size":0},{"associationFileName":"86_【专栏赠课】52《想你的时候问月亮》教唱(1).mp4","associationFilePath":"/2500/【目录】歌唱黄金知识点_精练歌曲【歌唱宝典】/86_【专栏赠课】52《想你的时候问月亮》教唱(1).mp4","associationFileId":837981950058544,"associationType":1,"category":1,"isDir":0,"pathId":19794,"size":0},{"associationFileName":"87_【专栏赠课】51《红颜知己》教唱(2).mp4","associationFilePath":"/2500/【目录】歌唱黄金知识点_精练歌曲【歌唱宝典】/87_【专栏赠课】51《红颜知己》教唱(2).mp4","associationFileId":220954054181376,"associationType":1,"category":1,"isDir":0,"pathId":19794,"size":0},{"associationFileName":"88_【专栏赠课】50《红颜知己》教唱(1).mp4","associationFilePath":"/2500/【目录】歌唱黄金知识点_精练歌曲【歌唱宝典】/88_【专栏赠课】50《红颜知己》教唱(1).mp4","associationFileId":1116390820437876,"associationType":1,"category":1,"isDir":0,"pathId":19794,"size":0},{"associationFileName":"89_【专栏赠课】49《站着等你三千年》教唱(2).mp4","associationFilePath":"/2500/【目录】歌唱黄金知识点_精练歌曲【歌唱宝典】/89_【专栏赠课】49《站着等你三千年》教唱(2).mp4","associationFileId":342655118704184,"associationType":1,"category":1,"isDir":0,"pathId":19794,"size":0},{"associationFileName":"90_【专栏赠课】48《站着等你三千年》教唱(1).mp4","associationFilePath":"/2500/【目录】歌唱黄金知识点_精练歌曲【歌唱宝典】/90_【专栏赠课】48《站着等你三千年》教唱(1).mp4","associationFileId":469076101538142,"associationType":1,"category":1,"isDir":0,"pathId":19794,"size":0},{"associationFileName":"91_【专栏赠课】47《夜夜夜漫长》教唱(2).mp4","associationFilePath":"/2500/【目录】歌唱黄金知识点_精练歌曲【歌唱宝典】/91_【专栏赠课】47《夜夜夜漫长》教唱(2).mp4","associationFileId":852339824381900,"associationType":1,"category":1,"isDir":0,"pathId":19794,"size":0},{"associationFileName":"92_【专栏赠课】46《夜夜夜漫长》教唱(1).mp4","associationFilePath":"/2500/【目录】歌唱黄金知识点_精练歌曲【歌唱宝典】/92_【专栏赠课】46《夜夜夜漫长》教唱(1).mp4","associationFileId":390887744319937,"associationType":1,"category":1,"isDir":0,"pathId":19794,"size":0},{"associationFileName":"93_【专栏赠课】45《爱琴海》教唱(2).mp4","associationFilePath":"/2500/【目录】歌唱黄金知识点_精练歌曲【歌唱宝典】/93_【专栏赠课】45《爱琴海》教唱(2).mp4","associationFileId":961684251597462,"associationType":1,"category":1,"isDir":0,"pathId":19794,"size":0},{"associationFileName":"94_【专栏赠课】44《爱琴海》教唱(1).mp4","associationFilePath":"/2500/【目录】歌唱黄金知识点_精练歌曲【歌唱宝典】/94_【专栏赠课】44《爱琴海》教唱(1).mp4","associationFileId":763354259621424,"associationType":1,"category":1,"isDir":0,"pathId":19794,"size":0},{"associationFileName":"95_【专栏赠课】42《西海情歌》教唱(1).mp4","associationFilePath":"/2500/【目录】歌唱黄金知识点_精练歌曲【歌唱宝典】/95_【专栏赠课】42《西海情歌》教唱(1).mp4","associationFileId":1110568859671789,"associationType":1,"category":1,"isDir":0,"pathId":19794,"size":0},{"associationFileName":"96_【专栏赠课】41《万疆》教唱.mp4","associationFilePath":"/2500/【目录】歌唱黄金知识点_精练歌曲【歌唱宝典】/96_【专栏赠课】41《万疆》教唱.mp4","associationFileId":161156882768676,"associationType":1,"category":1,"isDir":0,"pathId":19794,"size":0},{"associationFileName":"97_【专栏赠课】40《父亲》教唱(2).mp4","associationFilePath":"/2500/【目录】歌唱黄金知识点_精练歌曲【歌唱宝典】/97_【专栏赠课】40《父亲》教唱(2).mp4","associationFileId":27749975888504,"associationType":1,"category":1,"isDir":0,"pathId":19794,"size":0},{"associationFileName":"98_【专栏赠课】39《父亲》教唱(1).mp4","associationFilePath":"/2500/【目录】歌唱黄金知识点_精练歌曲【歌唱宝典】/98_【专栏赠课】39《父亲》教唱(1).mp4","associationFileId":782270493006324,"associationType":1,"category":1,"isDir":0,"pathId":19794,"size":0},{"associationFileName":"99_【专栏赠课】38《游牧时光》教唱(2).mp4","associationFilePath":"/2500/【目录】歌唱黄金知识点_精练歌曲【歌唱宝典】/99_【专栏赠课】38《游牧时光》教唱(2).mp4","associationFileId":1021520728260893,"associationType":1,"category":1,"isDir":0,"pathId":19794,"size":0}],"more":false,"page":1,"pageSize":500}