{"data":[{"associationFileName":"资料","associationFilePath":"/21000/【目录】【25节-￥699】1688店铺爆款打造流程.20节超全面干货内容.总时长近7小时_习羽说运营/资料","associationFileId":437625373042347,"associationType":1,"category":6,"isDir":1,"pathId":19991,"size":0},{"associationFileName":"01_第一节：1688爆款打造--开课思路篇.mp4","associationFilePath":"/21000/【目录】【25节-￥699】1688店铺爆款打造流程.20节超全面干货内容.总时长近7小时_习羽说运营/01_第一节：1688爆款打造--开课思路篇.mp4","associationFileId":76551176013722,"associationType":1,"category":1,"isDir":0,"pathId":19991,"size":0},{"associationFileName":"02_第二节：数据化选品-市场行业大盘数据分析及产品设计开发思路.mp4","associationFilePath":"/21000/【目录】【25节-￥699】1688店铺爆款打造流程.20节超全面干货内容.总时长近7小时_习羽说运营/02_第二节：数据化选品-市场行业大盘数据分析及产品设计开发思路.mp4","associationFileId":1075750006181529,"associationType":1,"category":1,"isDir":0,"pathId":19991,"size":0},{"associationFileName":"03_第三节：数据化选品-店内现有产品选品方法步骤.mp4","associationFilePath":"/21000/【目录】【25节-￥699】1688店铺爆款打造流程.20节超全面干货内容.总时长近7小时_习羽说运营/03_第三节：数据化选品-店内现有产品选品方法步骤.mp4","associationFileId":1049660467161597,"associationType":1,"category":1,"isDir":0,"pathId":19991,"size":0},{"associationFileName":"04_第四节：数据化选品-选品注意事项.mp4","associationFilePath":"/21000/【目录】【25节-￥699】1688店铺爆款打造流程.20节超全面干货内容.总时长近7小时_习羽说运营/04_第四节：数据化选品-选品注意事项.mp4","associationFileId":1110729423098144,"associationType":1,"category":1,"isDir":0,"pathId":19991,"size":0},{"associationFileName":"05_第五节：产品内功打造--优质标题撰写.mp4","associationFilePath":"/21000/【目录】【25节-￥699】1688店铺爆款打造流程.20节超全面干货内容.总时长近7小时_习羽说运营/05_第五节：产品内功打造--优质标题撰写.mp4","associationFileId":758254040530850,"associationType":1,"category":1,"isDir":0,"pathId":19991,"size":0},{"associationFileName":"06_第六节：产品内功打造--高点击率主图的设计方法.mp4","associationFilePath":"/21000/【目录】【25节-￥699】1688店铺爆款打造流程.20节超全面干货内容.总时长近7小时_习羽说运营/06_第六节：产品内功打造--高点击率主图的设计方法.mp4","associationFileId":114227168445701,"associationType":1,"category":1,"isDir":0,"pathId":19991,"size":0},{"associationFileName":"07_第七节：产品内功打造--高转化详情页设计方法.mp4","associationFilePath":"/21000/【目录】【25节-￥699】1688店铺爆款打造流程.20节超全面干货内容.总时长近7小时_习羽说运营/07_第七节：产品内功打造--高转化详情页设计方法.mp4","associationFileId":798079292198487,"associationType":1,"category":1,"isDir":0,"pathId":19991,"size":0},{"associationFileName":"08_第八节：产品内功打造--详情页数据诊断方法步骤.mp4","associationFilePath":"/21000/【目录】【25节-￥699】1688店铺爆款打造流程.20节超全面干货内容.总时长近7小时_习羽说运营/08_第八节：产品内功打造--详情页数据诊断方法步骤.mp4","associationFileId":66194143889730,"associationType":1,"category":1,"isDir":0,"pathId":19991,"size":0},{"associationFileName":"09_第九节：产品内功打造--高转化营销视频拍摄方法步骤.mp4","associationFilePath":"/21000/【目录】【25节-￥699】1688店铺爆款打造流程.20节超全面干货内容.总时长近7小时_习羽说运营/09_第九节：产品内功打造--高转化营销视频拍摄方法步骤.mp4","associationFileId":907444303079517,"associationType":1,"category":1,"isDir":0,"pathId":19991,"size":0},{"associationFileName":"10_第十节：产品内功打造--关联营销+优质评价布局.mp4","associationFilePath":"/21000/【目录】【25节-￥699】1688店铺爆款打造流程.20节超全面干货内容.总时长近7小时_习羽说运营/10_第十节：产品内功打造--关联营销+优质评价布局.mp4","associationFileId":693618749765411,"associationType":1,"category":1,"isDir":0,"pathId":19991,"size":0},{"associationFileName":"11_第十一节：爆款测款三步曲--老客+活动测款.mp4","associationFilePath":"/21000/【目录】【25节-￥699】1688店铺爆款打造流程.20节超全面干货内容.总时长近7小时_习羽说运营/11_第十一节：爆款测款三步曲--老客+活动测款.mp4","associationFileId":97330807491906,"associationType":1,"category":1,"isDir":0,"pathId":19991,"size":0},{"associationFileName":"12_第十二节：测款三步曲--数字营销测款①（全部工具特点解析）.mp4","associationFilePath":"/21000/【目录】【25节-￥699】1688店铺爆款打造流程.20节超全面干货内容.总时长近7小时_习羽说运营/12_第十二节：测款三步曲--数字营销测款①（全部工具特点解析）.mp4","associationFileId":154743897982910,"associationType":1,"category":1,"isDir":0,"pathId":19991,"size":0},{"associationFileName":"13_第十三节：测款三步曲--数字营销测款②（自助推广方法步骤）.mp4","associationFilePath":"/21000/【目录】【25节-￥699】1688店铺爆款打造流程.20节超全面干货内容.总时长近7小时_习羽说运营/13_第十三节：测款三步曲--数字营销测款②（自助推广方法步骤）.mp4","associationFileId":520996807115871,"associationType":1,"category":1,"isDir":0,"pathId":19991,"size":0},{"associationFileName":"14_第十四节：测款三步曲--数字营销测款③（全工具实操演练）.mp4","associationFilePath":"/21000/【目录】【25节-￥699】1688店铺爆款打造流程.20节超全面干货内容.总时长近7小时_习羽说运营/14_第十四节：测款三步曲--数字营销测款③（全工具实操演练）.mp4","associationFileId":460044724878600,"associationType":1,"category":1,"isDir":0,"pathId":19991,"size":0},{"associationFileName":"15_第十五节：测款三步曲--数字营销测款④（数字营销诊断优化）.mp4","associationFilePath":"/21000/【目录】【25节-￥699】1688店铺爆款打造流程.20节超全面干货内容.总时长近7小时_习羽说运营/15_第十五节：测款三步曲--数字营销测款④（数字营销诊断优化）.mp4","associationFileId":941897547022287,"associationType":1,"category":1,"isDir":0,"pathId":19991,"size":0},{"associationFileName":"16_第十六节：推爆流程--金冠品+镇店之宝助推流量.mp4","associationFilePath":"/21000/【目录】【25节-￥699】1688店铺爆款打造流程.20节超全面干货内容.总时长近7小时_习羽说运营/16_第十六节：推爆流程--金冠品+镇店之宝助推流量.mp4","associationFileId":5247399102051,"associationType":1,"category":1,"isDir":0,"pathId":19991,"size":0},{"associationFileName":"17_第十七节：推爆流程--如何做数据提升+老客转化助推交易.mp4","associationFilePath":"/21000/【目录】【25节-￥699】1688店铺爆款打造流程.20节超全面干货内容.总时长近7小时_习羽说运营/17_第十七节：推爆流程--如何做数据提升+老客转化助推交易.mp4","associationFileId":956427272320029,"associationType":1,"category":1,"isDir":0,"pathId":19991,"size":0},{"associationFileName":"18_第十八节：推爆流程--营销布局增加爆品流量.mp4","associationFilePath":"/21000/【目录】【25节-￥699】1688店铺爆款打造流程.20节超全面干货内容.总时长近7小时_习羽说运营/18_第十八节：推爆流程--营销布局增加爆品流量.mp4","associationFileId":875944313364295,"associationType":1,"category":1,"isDir":0,"pathId":19991,"size":0},{"associationFileName":"19_第十九节：推爆流程--付费+直播+横向市场.mp4","associationFilePath":"/21000/【目录】【25节-￥699】1688店铺爆款打造流程.20节超全面干货内容.总时长近7小时_习羽说运营/19_第十九节：推爆流程--付费+直播+横向市场.mp4","associationFileId":913873675565209,"associationType":1,"category":1,"isDir":0,"pathId":19991,"size":0},{"associationFileName":"20_第二十节：推爆流程--每个阶段应该做什么动作及达到什么标准？.mp4","associationFilePath":"/21000/【目录】【25节-￥699】1688店铺爆款打造流程.20节超全面干货内容.总时长近7小时_习羽说运营/20_第二十节：推爆流程--每个阶段应该做什么动作及达到什么标准？.mp4","associationFileId":965279329176058,"associationType":1,"category":1,"isDir":0,"pathId":19991,"size":0},{"associationFileName":"21_第二十一节：爆款维护的意义是什么？.mp4","associationFilePath":"/21000/【目录】【25节-￥699】1688店铺爆款打造流程.20节超全面干货内容.总时长近7小时_习羽说运营/21_第二十一节：爆款维护的意义是什么？.mp4","associationFileId":807006192829035,"associationType":1,"category":1,"isDir":0,"pathId":19991,"size":0},{"associationFileName":"22_第二十二节：爆款维护--数据维护方法.mp4","associationFilePath":"/21000/【目录】【25节-￥699】1688店铺爆款打造流程.20节超全面干货内容.总时长近7小时_习羽说运营/22_第二十二节：爆款维护--数据维护方法.mp4","associationFileId":187735045548247,"associationType":1,"category":1,"isDir":0,"pathId":19991,"size":0},{"associationFileName":"23_第二十三节：爆款维护--服务板块维护方法.mp4","associationFilePath":"/21000/【目录】【25节-￥699】1688店铺爆款打造流程.20节超全面干货内容.总时长近7小时_习羽说运营/23_第二十三节：爆款维护--服务板块维护方法.mp4","associationFileId":3714652905008,"associationType":1,"category":1,"isDir":0,"pathId":19991,"size":0},{"associationFileName":"24_第二十四节：爆款维护--营销板块维护.mp4","associationFilePath":"/21000/【目录】【25节-￥699】1688店铺爆款打造流程.20节超全面干货内容.总时长近7小时_习羽说运营/24_第二十四节：爆款维护--营销板块维护.mp4","associationFileId":938664030703719,"associationType":1,"category":1,"isDir":0,"pathId":19991,"size":0},{"associationFileName":"25_2023年如何通过数据规划产品①.mp4","associationFilePath":"/21000/【目录】【25节-￥699】1688店铺爆款打造流程.20节超全面干货内容.总时长近7小时_习羽说运营/25_2023年如何通过数据规划产品①.mp4","associationFileId":250913412313943,"associationType":1,"category":1,"isDir":0,"pathId":19991,"size":0}],"more":false,"page":1,"pageSize":500}