{"data":[{"associationFileName":"01_第一节-《漫步街上》-如何稳定喉部位置.mp4","associationFilePath":"/18500/【目录】SVIP尊享_万丹老师的美声课堂/01_第一节-《漫步街上》-如何稳定喉部位置.mp4","associationFileId":532537341839368,"associationType":1,"category":1,"isDir":0,"pathId":19938,"size":0},{"associationFileName":"02_第二节《故原草》-后咽壁的力量.mp4","associationFilePath":"/18500/【目录】SVIP尊享_万丹老师的美声课堂/02_第二节《故原草》-后咽壁的力量.mp4","associationFileId":426004687053685,"associationType":1,"category":1,"isDir":0,"pathId":19938,"size":0},{"associationFileName":"03_第三节《我感到》-如何正确运用、控制气息(1).mp4","associationFilePath":"/18500/【目录】SVIP尊享_万丹老师的美声课堂/03_第三节《我感到》-如何正确运用、控制气息(1).mp4","associationFileId":1078496386095363,"associationType":1,"category":1,"isDir":0,"pathId":19938,"size":0},{"associationFileName":"03_第三节《我感到》-如何正确运用、控制气息.mp4","associationFilePath":"/18500/【目录】SVIP尊享_万丹老师的美声课堂/03_第三节《我感到》-如何正确运用、控制气息.mp4","associationFileId":315888307736270,"associationType":1,"category":1,"isDir":0,"pathId":19938,"size":0},{"associationFileName":"04_第四节《玫瑰三愿》-如何理解腔体打开.mp4","associationFilePath":"/18500/【目录】SVIP尊享_万丹老师的美声课堂/04_第四节《玫瑰三愿》-如何理解腔体打开.mp4","associationFileId":591484579033478,"associationType":1,"category":1,"isDir":0,"pathId":19938,"size":0},{"associationFileName":"05_第五节《献词》-关于德语的辅音.mp4","associationFilePath":"/18500/【目录】SVIP尊享_万丹老师的美声课堂/05_第五节《献词》-关于德语的辅音.mp4","associationFileId":358615158737178,"associationType":1,"category":1,"isDir":0,"pathId":19938,"size":0},{"associationFileName":"06_第六节《奉献》-关于艺术歌曲的风格把握.mp4","associationFilePath":"/18500/【目录】SVIP尊享_万丹老师的美声课堂/06_第六节《奉献》-关于艺术歌曲的风格把握.mp4","associationFileId":418298954912787,"associationType":1,"category":1,"isDir":0,"pathId":19938,"size":0},{"associationFileName":"07_第七节《咪咪的告别》-高音不“冒”，低音不-“塌”.mp4","associationFilePath":"/18500/【目录】SVIP尊享_万丹老师的美声课堂/07_第七节《咪咪的告别》-高音不“冒”，低音不-“塌”.mp4","associationFileId":98317647756567,"associationType":1,"category":1,"isDir":0,"pathId":19938,"size":0},{"associationFileName":"08_第八节-《鸟儿在风中歌唱》-什么是真正的高位置.mp4","associationFilePath":"/18500/【目录】SVIP尊享_万丹老师的美声课堂/08_第八节-《鸟儿在风中歌唱》-什么是真正的高位置.mp4","associationFileId":497144032279688,"associationType":1,"category":1,"isDir":0,"pathId":19938,"size":0},{"associationFileName":"09_第九节-《再见我将去远方》-如何做渐强渐弱.mp4","associationFilePath":"/18500/【目录】SVIP尊享_万丹老师的美声课堂/09_第九节-《再见我将去远方》-如何做渐强渐弱.mp4","associationFileId":102405757067558,"associationType":1,"category":1,"isDir":0,"pathId":19938,"size":0},{"associationFileName":"10_第十节-学员汇报表演-课程总结.mp4","associationFilePath":"/18500/【目录】SVIP尊享_万丹老师的美声课堂/10_第十节-学员汇报表演-课程总结.mp4","associationFileId":673469051872346,"associationType":1,"category":1,"isDir":0,"pathId":19938,"size":0},{"associationFileName":"11_彩蛋课程.mp4","associationFilePath":"/18500/【目录】SVIP尊享_万丹老师的美声课堂/11_彩蛋课程.mp4","associationFileId":189666518984949,"associationType":1,"category":1,"isDir":0,"pathId":19938,"size":0},{"associationFileName":"【资料】00.漫步街上.pdf","associationFilePath":"/18500/【目录】SVIP尊享_万丹老师的美声课堂/【资料】00.漫步街上.pdf","associationFileId":1108196693368638,"associationType":1,"category":4,"isDir":0,"pathId":19938,"size":0},{"associationFileName":"【资料】01.故原草.pdf","associationFilePath":"/18500/【目录】SVIP尊享_万丹老师的美声课堂/【资料】01.故原草.pdf","associationFileId":550251058617715,"associationType":1,"category":4,"isDir":0,"pathId":19938,"size":0},{"associationFileName":"【资料】02.我感到.pdf","associationFilePath":"/18500/【目录】SVIP尊享_万丹老师的美声课堂/【资料】02.我感到.pdf","associationFileId":648959698771515,"associationType":1,"category":4,"isDir":0,"pathId":19938,"size":0},{"associationFileName":"【资料】03.艺术歌曲——M-玫瑰三愿.pdf","associationFilePath":"/18500/【目录】SVIP尊享_万丹老师的美声课堂/【资料】03.艺术歌曲——M-玫瑰三愿.pdf","associationFileId":607927910727934,"associationType":1,"category":4,"isDir":0,"pathId":19938,"size":0},{"associationFileName":"【资料】04.献词widmung 降A 舒曼op25-1.pdf","associationFilePath":"/18500/【目录】SVIP尊享_万丹老师的美声课堂/【资料】04.献词widmung 降A 舒曼op25-1.pdf","associationFileId":767213986715193,"associationType":1,"category":4,"isDir":0,"pathId":19938,"size":0},{"associationFileName":"【资料】05.奉献 - 理查·施特劳斯.pdf","associationFilePath":"/18500/【目录】SVIP尊享_万丹老师的美声课堂/【资料】05.奉献 - 理查·施特劳斯.pdf","associationFileId":214196203397412,"associationType":1,"category":4,"isDir":0,"pathId":19938,"size":0},{"associationFileName":"【资料】06.咪咪的告别.pdf","associationFilePath":"/18500/【目录】SVIP尊享_万丹老师的美声课堂/【资料】06.咪咪的告别.pdf","associationFileId":1115298216655298,"associationType":1,"category":4,"isDir":0,"pathId":19938,"size":0},{"associationFileName":"【资料】07.鸟儿在风中歌唱 降A.pdf","associationFilePath":"/18500/【目录】SVIP尊享_万丹老师的美声课堂/【资料】07.鸟儿在风中歌唱 降A.pdf","associationFileId":509881524281232,"associationType":1,"category":4,"isDir":0,"pathId":19938,"size":0},{"associationFileName":"【资料】08.再见我将去远方 C.pdf","associationFilePath":"/18500/【目录】SVIP尊享_万丹老师的美声课堂/【资料】08.再见我将去远方 C.pdf","associationFileId":1057586134638150,"associationType":1,"category":4,"isDir":0,"pathId":19938,"size":0}],"more":false,"page":1,"pageSize":500}