{"data":[{"associationFileName":"10：张书勇老师新架一路08讲.mp4","associationFilePath":"/25500/【目录】2478_陈氏太极拳新架一路21/10：张书勇老师新架一路08讲.mp4","associationFileId":25092132453933,"associationType":1,"category":1,"isDir":0,"pathId":20002,"size":0},{"associationFileName":"11：张书勇老师新架一路14讲.mp4","associationFilePath":"/25500/【目录】2478_陈氏太极拳新架一路21/11：张书勇老师新架一路14讲.mp4","associationFileId":381398104964058,"associationType":1,"category":1,"isDir":0,"pathId":20002,"size":0},{"associationFileName":"12：张书勇老师新架一路12期.mp4","associationFilePath":"/25500/【目录】2478_陈氏太极拳新架一路21/12：张书勇老师新架一路12期.mp4","associationFileId":61183625822433,"associationType":1,"category":1,"isDir":0,"pathId":20002,"size":0},{"associationFileName":"13：张书勇老师新架一路15讲.mp4","associationFilePath":"/25500/【目录】2478_陈氏太极拳新架一路21/13：张书勇老师新架一路15讲.mp4","associationFileId":434818187438941,"associationType":1,"category":1,"isDir":0,"pathId":20002,"size":0},{"associationFileName":"14：张书勇老师新架一路13期.mp4","associationFilePath":"/25500/【目录】2478_陈氏太极拳新架一路21/14：张书勇老师新架一路13期.mp4","associationFileId":1098349025743295,"associationType":1,"category":1,"isDir":0,"pathId":20002,"size":0},{"associationFileName":"15：张书勇老师新架一路11讲.mp4","associationFilePath":"/25500/【目录】2478_陈氏太极拳新架一路21/15：张书勇老师新架一路11讲.mp4","associationFileId":973255259268099,"associationType":1,"category":1,"isDir":0,"pathId":20002,"size":0},{"associationFileName":"16：张书勇老师新架一路16讲.mp4","associationFilePath":"/25500/【目录】2478_陈氏太极拳新架一路21/16：张书勇老师新架一路16讲.mp4","associationFileId":112820690422534,"associationType":1,"category":1,"isDir":0,"pathId":20002,"size":0},{"associationFileName":"17：张书勇老师新架一路17讲.mp4","associationFilePath":"/25500/【目录】2478_陈氏太极拳新架一路21/17：张书勇老师新架一路17讲.mp4","associationFileId":160943412872697,"associationType":1,"category":1,"isDir":0,"pathId":20002,"size":0},{"associationFileName":"18：张书勇老师新架一路19讲.mp4","associationFilePath":"/25500/【目录】2478_陈氏太极拳新架一路21/18：张书勇老师新架一路19讲.mp4","associationFileId":969881606277189,"associationType":1,"category":1,"isDir":0,"pathId":20002,"size":0},{"associationFileName":"19：张书勇老师新架一路21讲.mp4","associationFilePath":"/25500/【目录】2478_陈氏太极拳新架一路21/19：张书勇老师新架一路21讲.mp4","associationFileId":275321188561149,"associationType":1,"category":1,"isDir":0,"pathId":20002,"size":0},{"associationFileName":"1：第五期直播.mp4","associationFilePath":"/25500/【目录】2478_陈氏太极拳新架一路21/1：第五期直播.mp4","associationFileId":726208598368756,"associationType":1,"category":1,"isDir":0,"pathId":20002,"size":0},{"associationFileName":"20：张书勇老师新架一路18讲.mp4","associationFilePath":"/25500/【目录】2478_陈氏太极拳新架一路21/20：张书勇老师新架一路18讲.mp4","associationFileId":889899061162643,"associationType":1,"category":1,"isDir":0,"pathId":20002,"size":0},{"associationFileName":"21：张书勇老师新架一路20讲（改）.mp4","associationFilePath":"/25500/【目录】2478_陈氏太极拳新架一路21/21：张书勇老师新架一路20讲（改）.mp4","associationFileId":110351770872084,"associationType":1,"category":1,"isDir":0,"pathId":20002,"size":0},{"associationFileName":"2：张书勇 新架一路 第二期.mp4","associationFilePath":"/25500/【目录】2478_陈氏太极拳新架一路21/2：张书勇 新架一路 第二期.mp4","associationFileId":428171470685746,"associationType":1,"category":1,"isDir":0,"pathId":20002,"size":0},{"associationFileName":"3：第四期直播.mp4","associationFilePath":"/25500/【目录】2478_陈氏太极拳新架一路21/3：第四期直播.mp4","associationFileId":415578814089297,"associationType":1,"category":1,"isDir":0,"pathId":20002,"size":0},{"associationFileName":"4：张书勇 新架一路 第三期.mp4","associationFilePath":"/25500/【目录】2478_陈氏太极拳新架一路21/4：张书勇 新架一路 第三期.mp4","associationFileId":159864381017676,"associationType":1,"category":1,"isDir":0,"pathId":20002,"size":0},{"associationFileName":"5：张书勇 新架一路 第一期.mp4","associationFilePath":"/25500/【目录】2478_陈氏太极拳新架一路21/5：张书勇 新架一路 第一期.mp4","associationFileId":574373281725646,"associationType":1,"category":1,"isDir":0,"pathId":20002,"size":0},{"associationFileName":"6：张书勇老师新架一路10讲.mp4","associationFilePath":"/25500/【目录】2478_陈氏太极拳新架一路21/6：张书勇老师新架一路10讲.mp4","associationFileId":1087709289351218,"associationType":1,"category":1,"isDir":0,"pathId":20002,"size":0},{"associationFileName":"7：张书勇老师新架一路06讲.mp4","associationFilePath":"/25500/【目录】2478_陈氏太极拳新架一路21/7：张书勇老师新架一路06讲.mp4","associationFileId":637694805226852,"associationType":1,"category":1,"isDir":0,"pathId":20002,"size":0},{"associationFileName":"8：张书勇老师新架一路09讲.mp4","associationFilePath":"/25500/【目录】2478_陈氏太极拳新架一路21/8：张书勇老师新架一路09讲.mp4","associationFileId":224952876709427,"associationType":1,"category":1,"isDir":0,"pathId":20002,"size":0},{"associationFileName":"9：张书勇老师新架一路07讲.mp4","associationFilePath":"/25500/【目录】2478_陈氏太极拳新架一路21/9：张书勇老师新架一路07讲.mp4","associationFileId":106467700888852,"associationType":1,"category":1,"isDir":0,"pathId":20002,"size":0}],"more":false,"page":1,"pageSize":500}