{"data":[{"associationFileName":"{1}--《斌法》之实操篇","associationFilePath":"/查询目录/12-10/【目录】斌的世界-斌的吸引力课程/{1}--课程/{1}--《斌法》之实操篇","associationFileId":411492200346269,"associationType":1,"category":6,"isDir":1,"pathId":20661,"size":0},{"associationFileName":"{2}--《斌法》之心态篇","associationFilePath":"/查询目录/12-10/【目录】斌的世界-斌的吸引力课程/{1}--课程/{2}--《斌法》之心态篇","associationFileId":512829404171481,"associationType":1,"category":6,"isDir":1,"pathId":20661,"size":0},{"associationFileName":"{3}--斌哥：男性吸引力","associationFilePath":"/查询目录/12-10/【目录】斌的世界-斌的吸引力课程/{1}--课程/{3}--斌哥：男性吸引力","associationFileId":994923063450112,"associationType":1,"category":6,"isDir":1,"pathId":20661,"size":0},{"associationFileName":"{4}--两性关系深度刨析","associationFilePath":"/查询目录/12-10/【目录】斌的世界-斌的吸引力课程/{1}--课程/{4}--两性关系深度刨析","associationFileId":960295136133893,"associationType":1,"category":6,"isDir":1,"pathId":20661,"size":0}],"more":false,"page":1,"pageSize":500}