{"data":[{"associationFileName":"01 试听.mp4","associationFilePath":"/3000/【目录】华数之星-全新红宝书（二）小高组数论模块/01 试听.mp4","associationFileId":299954768211318,"associationType":1,"category":1,"isDir":0,"pathId":19804,"size":0},{"associationFileName":"02 第一讲 进制与整除特征.mp4","associationFilePath":"/3000/【目录】华数之星-全新红宝书（二）小高组数论模块/02 第一讲 进制与整除特征.mp4","associationFileId":436758803002195,"associationType":1,"category":1,"isDir":0,"pathId":19804,"size":0},{"associationFileName":"03 第二讲 因倍质he.mp4","associationFilePath":"/3000/【目录】华数之星-全新红宝书（二）小高组数论模块/03 第二讲 因倍质he.mp4","associationFileId":661520561819102,"associationType":1,"category":1,"isDir":0,"pathId":19804,"size":0},{"associationFileName":"04 第三讲同余.mp4","associationFilePath":"/3000/【目录】华数之星-全新红宝书（二）小高组数论模块/04 第三讲同余.mp4","associationFileId":1082158618323511,"associationType":1,"category":1,"isDir":0,"pathId":19804,"size":0},{"associationFileName":"05 第四讲孙子定理与费马小定理.mp4","associationFilePath":"/3000/【目录】华数之星-全新红宝书（二）小高组数论模块/05 第四讲孙子定理与费马小定理.mp4","associationFileId":1074265883053169,"associationType":1,"category":1,"isDir":0,"pathId":19804,"size":0},{"associationFileName":"06 第五讲不定方程.mp4","associationFilePath":"/3000/【目录】华数之星-全新红宝书（二）小高组数论模块/06 第五讲不定方程.mp4","associationFileId":263725952017639,"associationType":1,"category":1,"isDir":0,"pathId":19804,"size":0},{"associationFileName":"07 第一讲 提高练习.mp4","associationFilePath":"/3000/【目录】华数之星-全新红宝书（二）小高组数论模块/07 第一讲 提高练习.mp4","associationFileId":785396136311313,"associationType":1,"category":1,"isDir":0,"pathId":19804,"size":0},{"associationFileName":"08 第二讲 提高练习.mp4","associationFilePath":"/3000/【目录】华数之星-全新红宝书（二）小高组数论模块/08 第二讲 提高练习.mp4","associationFileId":240187039477336,"associationType":1,"category":1,"isDir":0,"pathId":19804,"size":0},{"associationFileName":"09 第三讲 提高练习.mp4","associationFilePath":"/3000/【目录】华数之星-全新红宝书（二）小高组数论模块/09 第三讲 提高练习.mp4","associationFileId":368221487363072,"associationType":1,"category":1,"isDir":0,"pathId":19804,"size":0},{"associationFileName":"10 第四讲 提高练习.mp4","associationFilePath":"/3000/【目录】华数之星-全新红宝书（二）小高组数论模块/10 第四讲 提高练习.mp4","associationFileId":569249337343911,"associationType":1,"category":1,"isDir":0,"pathId":19804,"size":0},{"associationFileName":"11 第五讲 提高练习.mp4","associationFilePath":"/3000/【目录】华数之星-全新红宝书（二）小高组数论模块/11 第五讲 提高练习.mp4","associationFileId":145662374690286,"associationType":1,"category":1,"isDir":0,"pathId":19804,"size":0}],"more":false,"page":1,"pageSize":500}