{"data":[{"associationFileName":"1_人体软组织压痛点推拿治疗常见类疾病线上网课（第一晚）——包寒毅.mp4","associationFilePath":"/4000/【目录】人体软组织压痛点推拿治疗常见类疾病线上网课——包寒毅/1_人体软组织压痛点推拿治疗常见类疾病线上网课（第一晚）——包寒毅.mp4","associationFileId":225961090424591,"associationType":1,"category":1,"isDir":0,"pathId":19806,"size":0},{"associationFileName":"2_人体软组织压痛点推拿治疗常见类疾病线上网课（第二晚）——包寒毅.mp4","associationFilePath":"/4000/【目录】人体软组织压痛点推拿治疗常见类疾病线上网课——包寒毅/2_人体软组织压痛点推拿治疗常见类疾病线上网课（第二晚）——包寒毅.mp4","associationFileId":237418436003115,"associationType":1,"category":1,"isDir":0,"pathId":19806,"size":0},{"associationFileName":"3_人体软组织压痛点推拿治疗常见类疾病线上网课（第三晚）——包寒毅.mp4","associationFilePath":"/4000/【目录】人体软组织压痛点推拿治疗常见类疾病线上网课——包寒毅/3_人体软组织压痛点推拿治疗常见类疾病线上网课（第三晚）——包寒毅.mp4","associationFileId":18292221133780,"associationType":1,"category":1,"isDir":0,"pathId":19806,"size":0}],"more":false,"page":1,"pageSize":500}