{"data":[{"associationFileName":"01_零基础也能成为小布改妆师先导片.mp4","associationFilePath":"/5000/【目录】（限时特惠）小布blythe改妆课程/01_零基础也能成为小布改妆师先导片.mp4","associationFileId":1032748812558550,"associationType":1,"category":1,"isDir":0,"pathId":19808,"size":0},{"associationFileName":"02_小布改妆师材料工具介绍.mp4","associationFilePath":"/5000/【目录】（限时特惠）小布blythe改妆课程/02_小布改妆师材料工具介绍.mp4","associationFileId":15521870465011,"associationType":1,"category":1,"isDir":0,"pathId":19808,"size":0},{"associationFileName":"03_1_小布无痕开脑_颅内结构与部件作用_磨改的意义_根据作品主题定调起稿.mp4","associationFilePath":"/5000/【目录】（限时特惠）小布blythe改妆课程/03_1_小布无痕开脑_颅内结构与部件作用_磨改的意义_根据作品主题定调起稿.mp4","associationFileId":438559245770820,"associationType":1,"category":1,"isDir":0,"pathId":19808,"size":0},{"associationFileName":"04_2.鼻子的结构分析_延伸设计_鼻子磨改实操_雕刻要点.mp4","associationFilePath":"/5000/【目录】（限时特惠）小布blythe改妆课程/04_2.鼻子的结构分析_延伸设计_鼻子磨改实操_雕刻要点.mp4","associationFileId":1109605243862387,"associationType":1,"category":1,"isDir":0,"pathId":19808,"size":0},{"associationFileName":"05_3.(上)嘴巴生理结构分析_闭嘴磨改雕刻要点与实操_下巴与腮边结构塑型.mp4","associationFilePath":"/5000/【目录】（限时特惠）小布blythe改妆课程/05_3.(上)嘴巴生理结构分析_闭嘴磨改雕刻要点与实操_下巴与腮边结构塑型.mp4","associationFileId":577825992657018,"associationType":1,"category":1,"isDir":0,"pathId":19808,"size":0},{"associationFileName":"06_4.（下）开嘴_小开心_吐舌_大笑_委屈嘟嘴_咬下唇结构变化与塑型要点_人中结构与雕刻实操_唇纹雕刻.mp4","associationFilePath":"/5000/【目录】（限时特惠）小布blythe改妆课程/06_4.（下）开嘴_小开心_吐舌_大笑_委屈嘟嘴_咬下唇结构变化与塑型要点_人中结构与雕刻实操_唇纹雕刻.mp4","associationFileId":1036209127516506,"associationType":1,"category":1,"isDir":0,"pathId":19808,"size":0},{"associationFileName":"07_5.泪沟磨改_双眼皮设计与雕刻技法_全脸脸型磨改塑型_全脸精细打磨_正确喷涂妆前消.mp4","associationFilePath":"/5000/【目录】（限时特惠）小布blythe改妆课程/07_5.泪沟磨改_双眼皮设计与雕刻技法_全脸脸型磨改塑型_全脸精细打磨_正确喷涂妆前消.mp4","associationFileId":465051542979290,"associationType":1,"category":1,"isDir":0,"pathId":19808,"size":0},{"associationFileName":"08_6.面部上妆_色彩知识与色调搭配_第一层妆面_底色渲染.mp4","associationFilePath":"/5000/【目录】（限时特惠）小布blythe改妆课程/08_6.面部上妆_色彩知识与色调搭配_第一层妆面_底色渲染.mp4","associationFileId":837027978793399,"associationType":1,"category":1,"isDir":0,"pathId":19808,"size":0},{"associationFileName":"09_7.第二层妆面：色彩层次提升_眉形设计思路_第三层妆面：眉毛、睫毛、双眼皮线条技法要诀.mp4","associationFilePath":"/5000/【目录】（限时特惠）小布blythe改妆课程/09_7.第二层妆面：色彩层次提升_眉形设计思路_第三层妆面：眉毛、睫毛、双眼皮线条技法要诀.mp4","associationFileId":542221425071784,"associationType":1,"category":1,"isDir":0,"pathId":19808,"size":0},{"associationFileName":"10_8.雀斑_血丝_血管_真人肌理_.mp4","associationFilePath":"/5000/【目录】（限时特惠）小布blythe改妆课程/10_8.雀斑_血丝_血管_真人肌理_.mp4","associationFileId":456056328371127,"associationType":1,"category":1,"isDir":0,"pathId":19808,"size":0},{"associationFileName":"11_9.树脂牙舌的制作与安装_眼皮装饰设计&手绘_后脑装饰设计&手绘.mp4","associationFilePath":"/5000/【目录】（限时特惠）小布blythe改妆课程/11_9.树脂牙舌的制作与安装_眼皮装饰设计&手绘_后脑装饰设计&手绘.mp4","associationFileId":569866718777736,"associationType":1,"category":1,"isDir":0,"pathId":19808,"size":0},{"associationFileName":"12_10.睫毛_眼片更换方法_风格搭配.mp4","associationFilePath":"/5000/【目录】（限时特惠）小布blythe改妆课程/12_10.睫毛_眼片更换方法_风格搭配.mp4","associationFileId":1040997565658115,"associationType":1,"category":1,"isDir":0,"pathId":19808,"size":0},{"associationFileName":"13_11_双拉绳改睡眼_开全眼_改T棒.mp4","associationFilePath":"/5000/【目录】（限时特惠）小布blythe改妆课程/13_11_双拉绳改睡眼_开全眼_改T棒.mp4","associationFileId":719120993207024,"associationType":1,"category":1,"isDir":0,"pathId":19808,"size":0},{"associationFileName":"14_12_素体各关节加固方法_脖卡的安装_头身组装.mp4","associationFilePath":"/5000/【目录】（限时特惠）小布blythe改妆课程/14_12_素体各关节加固方法_脖卡的安装_头身组装.mp4","associationFileId":766860453329038,"associationType":1,"category":1,"isDir":0,"pathId":19808,"size":0},{"associationFileName":"15_13_娃衣与配饰搭配_拍娃摄影技巧.mp4","associationFilePath":"/5000/【目录】（限时特惠）小布blythe改妆课程/15_13_娃衣与配饰搭配_拍娃摄影技巧.mp4","associationFileId":1105572053605832,"associationType":1,"category":1,"isDir":0,"pathId":19808,"size":0},{"associationFileName":"16_14_给娃娘的开箱惊喜_创业指导.mp4","associationFilePath":"/5000/【目录】（限时特惠）小布blythe改妆课程/16_14_给娃娘的开箱惊喜_创业指导.mp4","associationFileId":1075898542146773,"associationType":1,"category":1,"isDir":0,"pathId":19808,"size":0},{"associationFileName":"17_10【真人风基础眼纹眼片】.mp4","associationFilePath":"/5000/【目录】（限时特惠）小布blythe改妆课程/17_10【真人风基础眼纹眼片】.mp4","associationFileId":351629037681902,"associationType":1,"category":1,"isDir":0,"pathId":19808,"size":0},{"associationFileName":"18_9【简单5步的百搭眼片】.mp4","associationFilePath":"/5000/【目录】（限时特惠）小布blythe改妆课程/18_9【简单5步的百搭眼片】.mp4","associationFileId":646802864446900,"associationType":1,"category":1,"isDir":0,"pathId":19808,"size":0},{"associationFileName":"19_眼片课8【日拍风格眼片】.mp4","associationFilePath":"/5000/【目录】（限时特惠）小布blythe改妆课程/19_眼片课8【日拍风格眼片】.mp4","associationFileId":605635567432601,"associationType":1,"category":1,"isDir":0,"pathId":19808,"size":0},{"associationFileName":"20_眼片课7【马卡龙色系眼片】吐司君小布Blythe眼片从小白到大师的NewStart.mp4","associationFilePath":"/5000/【目录】（限时特惠）小布blythe改妆课程/20_眼片课7【马卡龙色系眼片】吐司君小布Blythe眼片从小白到大师的NewStart.mp4","associationFileId":227210772071083,"associationType":1,"category":1,"isDir":0,"pathId":19808,"size":0},{"associationFileName":"21_眼片课6【模具介绍】.mp4","associationFilePath":"/5000/【目录】（限时特惠）小布blythe改妆课程/21_眼片课6【模具介绍】.mp4","associationFileId":812412083320636,"associationType":1,"category":1,"isDir":0,"pathId":19808,"size":0},{"associationFileName":"22_眼片课5【工具选择与辅料选购】.mp4","associationFilePath":"/5000/【目录】（限时特惠）小布blythe改妆课程/22_眼片课5【工具选择与辅料选购】.mp4","associationFileId":347753048135460,"associationType":1,"category":1,"isDir":0,"pathId":19808,"size":0},{"associationFileName":"23_眼片课4【吐司底托的特点及注意事项】.mp4","associationFilePath":"/5000/【目录】（限时特惠）小布blythe改妆课程/23_眼片课4【吐司底托的特点及注意事项】.mp4","associationFileId":578595511221971,"associationType":1,"category":1,"isDir":0,"pathId":19808,"size":0},{"associationFileName":"24_眼片课3【中布与小布眼部结构】.mp4","associationFilePath":"/5000/【目录】（限时特惠）小布blythe改妆课程/24_眼片课3【中布与小布眼部结构】.mp4","associationFileId":857618270679937,"associationType":1,"category":1,"isDir":0,"pathId":19808,"size":0},{"associationFileName":"25_眼片课2【mini布泡泡布的眼部结构】.mp4","associationFilePath":"/5000/【目录】（限时特惠）小布blythe改妆课程/25_眼片课2【mini布泡泡布的眼部结构】.mp4","associationFileId":667775471147187,"associationType":1,"category":1,"isDir":0,"pathId":19808,"size":0}],"more":false,"page":1,"pageSize":500}