{"data":[{"associationFileName":"[10]--10探索三角形相似的条件.mp4","associationFilePath":"/8500/【目录】2023 探究应用新思维数学视频 九年级竞赛训练 南通名师主讲/[10]--10探索三角形相似的条件.mp4","associationFileId":127557912833202,"associationType":1,"category":1,"isDir":0,"pathId":19824,"size":0},{"associationFileName":"[11]--11 相似三角形的应用.mp4","associationFilePath":"/8500/【目录】2023 探究应用新思维数学视频 九年级竞赛训练 南通名师主讲/[11]--11 相似三角形的应用.mp4","associationFileId":210128970123508,"associationType":1,"category":1,"isDir":0,"pathId":19824,"size":0},{"associationFileName":"[12]--12图形的旋转.mp4","associationFilePath":"/8500/【目录】2023 探究应用新思维数学视频 九年级竞赛训练 南通名师主讲/[12]--12图形的旋转.mp4","associationFileId":269804767176232,"associationType":1,"category":1,"isDir":0,"pathId":19824,"size":0},{"associationFileName":"[13]--13圆的对称性.mp4","associationFilePath":"/8500/【目录】2023 探究应用新思维数学视频 九年级竞赛训练 南通名师主讲/[13]--13圆的对称性.mp4","associationFileId":207176095963902,"associationType":1,"category":1,"isDir":0,"pathId":19824,"size":0},{"associationFileName":"[14]--14圆中角.mp4","associationFilePath":"/8500/【目录】2023 探究应用新思维数学视频 九年级竞赛训练 南通名师主讲/[14]--14圆中角.mp4","associationFileId":627448104144884,"associationType":1,"category":1,"isDir":0,"pathId":19824,"size":0},{"associationFileName":"[15]--15直线与圆.mp4","associationFilePath":"/8500/【目录】2023 探究应用新思维数学视频 九年级竞赛训练 南通名师主讲/[15]--15直线与圆.mp4","associationFileId":433867186138278,"associationType":1,"category":1,"isDir":0,"pathId":19824,"size":0},{"associationFileName":"[16]--16与圆有关的计算.mp4","associationFilePath":"/8500/【目录】2023 探究应用新思维数学视频 九年级竞赛训练 南通名师主讲/[16]--16与圆有关的计算.mp4","associationFileId":239457360529727,"associationType":1,"category":1,"isDir":0,"pathId":19824,"size":0},{"associationFileName":"[17]--17锐角三角函数.mp4","associationFilePath":"/8500/【目录】2023 探究应用新思维数学视频 九年级竞赛训练 南通名师主讲/[17]--17锐角三角函数.mp4","associationFileId":573307831221628,"associationType":1,"category":1,"isDir":0,"pathId":19824,"size":0},{"associationFileName":"[1]--1 一元二次方程.mp4","associationFilePath":"/8500/【目录】2023 探究应用新思维数学视频 九年级竞赛训练 南通名师主讲/[1]--1 一元二次方程.mp4","associationFileId":507291934986518,"associationType":1,"category":1,"isDir":0,"pathId":19824,"size":0},{"associationFileName":"[2]--2 根的判别式.mp4","associationFilePath":"/8500/【目录】2023 探究应用新思维数学视频 九年级竞赛训练 南通名师主讲/[2]--2 根的判别式.mp4","associationFileId":44399900753596,"associationType":1,"category":1,"isDir":0,"pathId":19824,"size":0},{"associationFileName":"[3]--3 韦达定理.mp4","associationFilePath":"/8500/【目录】2023 探究应用新思维数学视频 九年级竞赛训练 南通名师主讲/[3]--3 韦达定理.mp4","associationFileId":60520151464995,"associationType":1,"category":1,"isDir":0,"pathId":19824,"size":0},{"associationFileName":"[4]--4 一元二次方程的应用.mp4","associationFilePath":"/8500/【目录】2023 探究应用新思维数学视频 九年级竞赛训练 南通名师主讲/[4]--4 一元二次方程的应用.mp4","associationFileId":1013496004245293,"associationType":1,"category":1,"isDir":0,"pathId":19824,"size":0},{"associationFileName":"[5]--5 反比例函数.mp4","associationFilePath":"/8500/【目录】2023 探究应用新思维数学视频 九年级竞赛训练 南通名师主讲/[5]--5 反比例函数.mp4","associationFileId":38390247606004,"associationType":1,"category":1,"isDir":0,"pathId":19824,"size":0},{"associationFileName":"[6]--6 二次函数的图象和性质.mp4","associationFilePath":"/8500/【目录】2023 探究应用新思维数学视频 九年级竞赛训练 南通名师主讲/[6]--6 二次函数的图象和性质.mp4","associationFileId":310044297000089,"associationType":1,"category":1,"isDir":0,"pathId":19824,"size":0},{"associationFileName":"[7]--7 二次函数的应用.mp4","associationFilePath":"/8500/【目录】2023 探究应用新思维数学视频 九年级竞赛训练 南通名师主讲/[7]--7 二次函数的应用.mp4","associationFileId":397479132430955,"associationType":1,"category":1,"isDir":0,"pathId":19824,"size":0},{"associationFileName":"[8]--8 抛物线与几何变换.mp4","associationFilePath":"/8500/【目录】2023 探究应用新思维数学视频 九年级竞赛训练 南通名师主讲/[8]--8 抛物线与几何变换.mp4","associationFileId":627926588918568,"associationType":1,"category":1,"isDir":0,"pathId":19824,"size":0},{"associationFileName":"[9]--9二次方程和二次函数.mp4","associationFilePath":"/8500/【目录】2023 探究应用新思维数学视频 九年级竞赛训练 南通名师主讲/[9]--9二次方程和二次函数.mp4","associationFileId":979275965437634,"associationType":1,"category":1,"isDir":0,"pathId":19824,"size":0}],"more":false,"page":1,"pageSize":500}