{"data":[{"associationFileName":"001.人性的本质（上）.mp3","associationFilePath":"/12000/【目录】2024破局天书：《用得上的人性大课》/001.人性的本质（上）.mp3","associationFileId":976886713723854,"associationType":1,"category":2,"isDir":0,"pathId":19925,"size":0},{"associationFileName":"002.人性的本质（下）.mp3","associationFilePath":"/12000/【目录】2024破局天书：《用得上的人性大课》/002.人性的本质（下）.mp3","associationFileId":760186831632717,"associationType":1,"category":2,"isDir":0,"pathId":19925,"size":0},{"associationFileName":"003.人性的四大陷阱：为什么吃大亏的总是你.mp3","associationFilePath":"/12000/【目录】2024破局天书：《用得上的人性大课》/003.人性的四大陷阱：为什么吃大亏的总是你.mp3","associationFileId":1097651284481818,"associationType":1,"category":2,"isDir":0,"pathId":19925,"size":0},{"associationFileName":"004.三个人性铁律，不能说，但你必须懂.mp3","associationFilePath":"/12000/【目录】2024破局天书：《用得上的人性大课》/004.三个人性铁律，不能说，但你必须懂.mp3","associationFileId":938154616683884,"associationType":1,"category":2,"isDir":0,"pathId":19925,"size":0},{"associationFileName":"005.财富的本质，是不和人性为敌.mp3","associationFilePath":"/12000/【目录】2024破局天书：《用得上的人性大课》/005.财富的本质，是不和人性为敌.mp3","associationFileId":682349690747672,"associationType":1,"category":2,"isDir":0,"pathId":19925,"size":0},{"associationFileName":"006.有些人为什么一辈子运气都不好？如何破解.mp3","associationFilePath":"/12000/【目录】2024破局天书：《用得上的人性大课》/006.有些人为什么一辈子运气都不好？如何破解.mp3","associationFileId":67769213612948,"associationType":1,"category":2,"isDir":0,"pathId":19925,"size":0},{"associationFileName":"007.如何摆脱原生家庭束缚，从此没有负担？.mp3","associationFilePath":"/12000/【目录】2024破局天书：《用得上的人性大课》/007.如何摆脱原生家庭束缚，从此没有负担？.mp3","associationFileId":491163074871962,"associationType":1,"category":2,"isDir":0,"pathId":19925,"size":0},{"associationFileName":"008.人性拿捏住了，就没有谈不好的爱情和婚姻.mp3","associationFilePath":"/12000/【目录】2024破局天书：《用得上的人性大课》/008.人性拿捏住了，就没有谈不好的爱情和婚姻.mp3","associationFileId":969021082318361,"associationType":1,"category":2,"isDir":0,"pathId":19925,"size":0},{"associationFileName":"009.如何利用人性，让对方越来越爱你.mp3","associationFilePath":"/12000/【目录】2024破局天书：《用得上的人性大课》/009.如何利用人性，让对方越来越爱你.mp3","associationFileId":415026272392143,"associationType":1,"category":2,"isDir":0,"pathId":19925,"size":0},{"associationFileName":"010.利用人性铁律，从婆媳敌对到婆媳共赢.mp3","associationFilePath":"/12000/【目录】2024破局天书：《用得上的人性大课》/010.利用人性铁律，从婆媳敌对到婆媳共赢.mp3","associationFileId":183802069553283,"associationType":1,"category":2,"isDir":0,"pathId":19925,"size":0},{"associationFileName":"011.人性解析1，为什么你付出越多越没有好结果？.mp3","associationFilePath":"/12000/【目录】2024破局天书：《用得上的人性大课》/011.人性解析1，为什么你付出越多越没有好结果？.mp3","associationFileId":122441295316604,"associationType":1,"category":2,"isDir":0,"pathId":19925,"size":0},{"associationFileName":"012.人性解析2，为什么有的人很难戒掉婚外情？.mp3","associationFilePath":"/12000/【目录】2024破局天书：《用得上的人性大课》/012.人性解析2，为什么有的人很难戒掉婚外情？.mp3","associationFileId":536418627348916,"associationType":1,"category":2,"isDir":0,"pathId":19925,"size":0},{"associationFileName":"013.如何摆脱涉恐，彻底爱上社交.mp3","associationFilePath":"/12000/【目录】2024破局天书：《用得上的人性大课》/013.如何摆脱涉恐，彻底爱上社交.mp3","associationFileId":159635898345264,"associationType":1,"category":2,"isDir":0,"pathId":19925,"size":0},{"associationFileName":"014.如何拒绝人而不得罪人，掌控全局？.mp3","associationFilePath":"/12000/【目录】2024破局天书：《用得上的人性大课》/014.如何拒绝人而不得罪人，掌控全局？.mp3","associationFileId":932916236526067,"associationType":1,"category":2,"isDir":0,"pathId":19925,"size":0},{"associationFileName":"015.必学的沟通方式，沟通能力涨10倍.mp3","associationFilePath":"/12000/【目录】2024破局天书：《用得上的人性大课》/015.必学的沟通方式，沟通能力涨10倍.mp3","associationFileId":529663622985081,"associationType":1,"category":2,"isDir":0,"pathId":19925,"size":0},{"associationFileName":"016.如何利用人性沟通，精准拿捏七寸？.mp3","associationFilePath":"/12000/【目录】2024破局天书：《用得上的人性大课》/016.如何利用人性沟通，精准拿捏七寸？.mp3","associationFileId":928316108272216,"associationType":1,"category":2,"isDir":0,"pathId":19925,"size":0},{"associationFileName":"017.普通人如何主动结交贵人？.mp3","associationFilePath":"/12000/【目录】2024破局天书：《用得上的人性大课》/017.普通人如何主动结交贵人？.mp3","associationFileId":16693641974202,"associationType":1,"category":2,"isDir":0,"pathId":19925,"size":0},{"associationFileName":"018.如何破解他人对你的人性操控？.mp3","associationFilePath":"/12000/【目录】2024破局天书：《用得上的人性大课》/018.如何破解他人对你的人性操控？.mp3","associationFileId":565914679248253,"associationType":1,"category":2,"isDir":0,"pathId":19925,"size":0},{"associationFileName":"019.为什么有的老板喜欢重用小人？.mp3","associationFilePath":"/12000/【目录】2024破局天书：《用得上的人性大课》/019.为什么有的老板喜欢重用小人？.mp3","associationFileId":688892887860464,"associationType":1,"category":2,"isDir":0,"pathId":19925,"size":0},{"associationFileName":"020.和领导沟通，善用人性这3招就够了!.mp3","associationFilePath":"/12000/【目录】2024破局天书：《用得上的人性大课》/020.和领导沟通，善用人性这3招就够了!.mp3","associationFileId":1114772234664050,"associationType":1,"category":2,"isDir":0,"pathId":19925,"size":0},{"associationFileName":"021.避开这5个职场禁忌，让你在职场出人头地.mp3","associationFilePath":"/12000/【目录】2024破局天书：《用得上的人性大课》/021.避开这5个职场禁忌，让你在职场出人头地.mp3","associationFileId":270345558916868,"associationType":1,"category":2,"isDir":0,"pathId":19925,"size":0},{"associationFileName":"022.如何听懂老板的话外音，摸清他的真实想法.mp3","associationFilePath":"/12000/【目录】2024破局天书：《用得上的人性大课》/022.如何听懂老板的话外音，摸清他的真实想法.mp3","associationFileId":112920195269904,"associationType":1,"category":2,"isDir":0,"pathId":19925,"size":0},{"associationFileName":"023.大家不说，但必须知道的职场潜规则.mp3","associationFilePath":"/12000/【目录】2024破局天书：《用得上的人性大课》/023.大家不说，但必须知道的职场潜规则.mp3","associationFileId":1003801549965339,"associationType":1,"category":2,"isDir":0,"pathId":19925,"size":0},{"associationFileName":"024.送礼和饭局的所有绝学，鱼跃龙门.mp3","associationFilePath":"/12000/【目录】2024破局天书：《用得上的人性大课》/024.送礼和饭局的所有绝学，鱼跃龙门.mp3","associationFileId":870597035996657,"associationType":1,"category":2,"isDir":0,"pathId":19925,"size":0},{"associationFileName":"025.如何在职场步步为营，成为老板心腹，独上青云？.mp3","associationFilePath":"/12000/【目录】2024破局天书：《用得上的人性大课》/025.如何在职场步步为营，成为老板心腹，独上青云？.mp3","associationFileId":1093542246620237,"associationType":1,"category":2,"isDir":0,"pathId":19925,"size":0},{"associationFileName":"026.最顶尖销售，是这样利用人性成交的.mp3","associationFilePath":"/12000/【目录】2024破局天书：《用得上的人性大课》/026.最顶尖销售，是这样利用人性成交的.mp3","associationFileId":1028682353629193,"associationType":1,"category":2,"isDir":0,"pathId":19925,"size":0},{"associationFileName":"027.不懂人性，对员工太好的老板下场都很惨.mp3","associationFilePath":"/12000/【目录】2024破局天书：《用得上的人性大课》/027.不懂人性，对员工太好的老板下场都很惨.mp3","associationFileId":644549427357205,"associationType":1,"category":2,"isDir":0,"pathId":19925,"size":0},{"associationFileName":"028.精通人性，如何驾驭不同性格的下属.mp3","associationFilePath":"/12000/【目录】2024破局天书：《用得上的人性大课》/028.精通人性，如何驾驭不同性格的下属.mp3","associationFileId":471149506101204,"associationType":1,"category":2,"isDir":0,"pathId":19925,"size":0},{"associationFileName":"029.人性逆流：贫穷的真相.mp3","associationFilePath":"/12000/【目录】2024破局天书：《用得上的人性大课》/029.人性逆流：贫穷的真相.mp3","associationFileId":853142553513624,"associationType":1,"category":2,"isDir":0,"pathId":19925,"size":0},{"associationFileName":"030.先克服这3种人性弱点，财富真挡不住.mp3","associationFilePath":"/12000/【目录】2024破局天书：《用得上的人性大课》/030.先克服这3种人性弱点，财富真挡不住.mp3","associationFileId":792881378616457,"associationType":1,"category":2,"isDir":0,"pathId":19925,"size":0},{"associationFileName":"031.你是怎么被人性套路“偷走”财富的？.mp3","associationFilePath":"/12000/【目录】2024破局天书：《用得上的人性大课》/031.你是怎么被人性套路“偷走”财富的？.mp3","associationFileId":146197307743256,"associationType":1,"category":2,"isDir":0,"pathId":19925,"size":0},{"associationFileName":"032.投资的底层逻辑，“保值”和反人性.mp3","associationFilePath":"/12000/【目录】2024破局天书：《用得上的人性大课》/032.投资的底层逻辑，“保值”和反人性.mp3","associationFileId":766548885703530,"associationType":1,"category":2,"isDir":0,"pathId":19925,"size":0},{"associationFileName":"033.最有钱那批富豪的高阶玩法：不外传的阳谋和阴谋.mp3","associationFilePath":"/12000/【目录】2024破局天书：《用得上的人性大课》/033.最有钱那批富豪的高阶玩法：不外传的阳谋和阴谋.mp3","associationFileId":36857976888070,"associationType":1,"category":2,"isDir":0,"pathId":19925,"size":0},{"associationFileName":"034.如何驾驭人性，人生逆风翻盘？.mp3","associationFilePath":"/12000/【目录】2024破局天书：《用得上的人性大课》/034.如何驾驭人性，人生逆风翻盘？.mp3","associationFileId":1114438032823451,"associationType":1,"category":2,"isDir":0,"pathId":19925,"size":0},{"associationFileName":"035.更新信息-图文.html","associationFilePath":"/12000/【目录】2024破局天书：《用得上的人性大课》/035.更新信息-图文.html","associationFileId":1002057237815250,"associationType":1,"category":4,"isDir":0,"pathId":19925,"size":0}],"more":false,"page":1,"pageSize":500}